{"name":"0","currentGameObject":{"instanceID":-58948914},"x":10.0,"y":1.1985886096954346,"z":1.0}{"name":"Underground0","currentGameObject":{"instanceID":-58948926},"x":10.0,"y":0.19858863949775697,"z":1.0}{"name":"Underground0","currentGameObject":{"instanceID":-58948936},"x":10.0,"y":-0.8014113903045654,"z":1.0}{"name":"Underground0","currentGameObject":{"instanceID":-58948946},"x":10.0,"y":-1.8014113903045655,"z":1.0}{"name":"0","currentGameObject":{"instanceID":-58948956},"x":11.0,"y":1.300178050994873,"z":1.0}{"name":"Underground0","currentGameObject":{"instanceID":-58948968},"x":11.0,"y":0.30017808079719546,"z":1.0}{"name":"Underground0","currentGameObject":{"instanceID":-58948980},"x":11.0,"y":-0.699821949005127,"z":1.0}{"name":"Underground0","currentGameObject":{"instanceID":-58948990},"x":11.0,"y":-1.699821949005127,"z":1.0}{"name":"0","currentGameObject":{"instanceID":-58949002},"x":12.0,"y":1.2877026796340943,"z":1.0}{"name":"Underground0","currentGameObject":{"instanceID":-58949014},"x":12.0,"y":0.2877027094364166,"z":1.0}{"name":"Underground0","currentGameObject":{"instanceID":-58949024},"x":12.0,"y":-0.7122973203659058,"z":1.0}{"name":"Underground0","currentGameObject":{"instanceID":-58949034},"x":12.0,"y":-1.7122973203659058,"z":1.0}{"name":"0","currentGameObject":{"instanceID":-58949046},"x":13.0,"y":1.4219913482666016,"z":1.0}{"name":"Underground0","currentGameObject":{"instanceID":-58949058},"x":13.0,"y":0.4219912886619568,"z":1.0}{"name":"Underground0","currentGameObject":{"instanceID":-58949070},"x":13.0,"y":-0.5780087113380432,"z":1.0}{"name":"Underground0","currentGameObject":{"instanceID":-58949080},"x":13.0,"y":-1.5780086517333985,"z":1.0}{"name":"0","currentGameObject":{"instanceID":-58949090},"x":14.0,"y":1.3839590549468995,"z":1.0}{"name":"Underground0","currentGameObject":{"instanceID":-58949110},"x":14.0,"y":0.3839591145515442,"z":1.0}{"name":"Underground0","currentGameObject":{"instanceID":-58949120},"x":14.0,"y":-0.6160408854484558,"z":1.0}{"name":"Underground0","currentGameObject":{"instanceID":-58949130},"x":14.0,"y":-1.6160409450531006,"z":1.0}{"name":"0","currentGameObject":{"instanceID":-58949142},"x":15.0,"y":1.198202133178711,"z":1.0}{"name":"Underground0","currentGameObject":{"instanceID":-58949154},"x":15.0,"y":0.19820210337638856,"z":1.0}{"name":"Underground0","currentGameObject":{"instanceID":-58949166},"x":15.0,"y":-0.8017978668212891,"z":1.0}{"name":"Underground0","currentGameObject":{"instanceID":-58949176},"x":15.0,"y":-1.801797866821289,"z":1.0}{"name":"0","currentGameObject":{"instanceID":-58949186},"x":16.0,"y":1.160705327987671,"z":1.0}{"name":"Underground0","currentGameObject":{"instanceID":-58949206},"x":16.0,"y":0.1607052981853485,"z":1.0}{"name":"Underground0","currentGameObject":{"instanceID":-58949216},"x":16.0,"y":-0.8392946720123291,"z":1.0}{"name":"Underground0","currentGameObject":{"instanceID":-58949226},"x":16.0,"y":-1.839294672012329,"z":1.0}{"name":"0","currentGameObject":{"instanceID":-58949238},"x":17.0,"y":1.1823660135269166,"z":1.0}{"name":"Underground0","currentGameObject":{"instanceID":-58949250},"x":17.0,"y":0.1823660433292389,"z":1.0}{"name":"Underground0","currentGameObject":{"instanceID":-58949260},"x":17.0,"y":-0.8176339864730835,"z":1.0}{"name":"Underground0","currentGameObject":{"instanceID":-58949272},"x":17.0,"y":-1.8176339864730836,"z":1.0}{"name":"0","currentGameObject":{"instanceID":-58949282},"x":18.0,"y":1.0291187763214112,"z":1.0}{"name":"Underground0","currentGameObject":{"instanceID":-58949294},"x":18.0,"y":0.029118716716766359,"z":1.0}{"name":"Underground0","currentGameObject":{"instanceID":-58949306},"x":18.0,"y":-0.9708812832832336,"z":1.0}{"name":"Underground0","currentGameObject":{"instanceID":-58949316},"x":18.0,"y":-1.9708812236785889,"z":1.0}{"name":"0","currentGameObject":{"instanceID":-58949326},"x":19.0,"y":1.1780672073364258,"z":1.0}{"name":"Underground0","currentGameObject":{"instanceID":-58949338},"x":19.0,"y":0.1780671775341034,"z":1.0}{"name":"Underground0","currentGameObject":{"instanceID":-58949350},"x":19.0,"y":-0.8219327926635742,"z":1.0}{"name":"Underground0","currentGameObject":{"instanceID":-58949362},"x":19.0,"y":-1.8219327926635743,"z":1.0}{"name":"0","currentGameObject":{"instanceID":-58949374},"x":10.0,"y":1.3580563068389893,"z":2.0}{"name":"Underground0","currentGameObject":{"instanceID":-58949386},"x":10.0,"y":0.35805630683898928,"z":2.0}{"name":"Underground0","currentGameObject":{"instanceID":-58949398},"x":10.0,"y":-0.6419436931610107,"z":2.0}{"name":"Underground0","currentGameObject":{"instanceID":-58949410},"x":10.0,"y":-1.6419436931610108,"z":2.0}{"name":"0","currentGameObject":{"instanceID":-58949422},"x":11.0,"y":1.1333342790603638,"z":2.0}{"name":"Underground0","currentGameObject":{"instanceID":-58949434},"x":11.0,"y":0.13333430886268617,"z":2.0}{"name":"Underground0","currentGameObject":{"instanceID":-58949446},"x":11.0,"y":-0.8666657209396362,"z":2.0}{"name":"Underground0","currentGameObject":{"instanceID":-58949456},"x":11.0,"y":-1.8666657209396363,"z":2.0}{"name":"0","currentGameObject":{"instanceID":-58949466},"x":12.0,"y":1.0908145904541016,"z":2.0}{"name":"Underground0","currentGameObject":{"instanceID":-58949478},"x":12.0,"y":0.09081459045410156,"z":2.0}{"name":"Underground0","currentGameObject":{"instanceID":-58949488},"x":12.0,"y":-0.9091854095458984,"z":2.0}{"name":"Underground0","currentGameObject":{"instanceID":-58949498},"x":12.0,"y":-1.9091854095458985,"z":2.0}{"name":"0","currentGameObject":{"instanceID":-58949510},"x":13.0,"y":1.1182804107666016,"z":2.0}{"name":"Underground0","currentGameObject":{"instanceID":-58949522},"x":13.0,"y":0.11828041076660156,"z":2.0}{"name":"Underground0","currentGameObject":{"instanceID":-58949532},"x":13.0,"y":-0.8817195892333984,"z":2.0}{"name":"Underground0","currentGameObject":{"instanceID":-58949542},"x":13.0,"y":-1.8817195892333985,"z":2.0}{"name":"0","currentGameObject":{"instanceID":-58949552},"x":14.0,"y":1.2575403451919556,"z":2.0}{"name":"Underground0","currentGameObject":{"instanceID":-58949572},"x":14.0,"y":0.25754037499427798,"z":2.0}{"name":"Underground0","currentGameObject":{"instanceID":-58949584},"x":14.0,"y":-0.7424596548080444,"z":2.0}{"name":"Underground0","currentGameObject":{"instanceID":-58949594},"x":14.0,"y":-1.7424596548080445,"z":2.0}{"name":"0","currentGameObject":{"instanceID":-58949604},"x":15.0,"y":1.0804394483566285,"z":2.0}{"name":"Underground0","currentGameObject":{"instanceID":-58949616},"x":15.0,"y":0.08043944835662842,"z":2.0}{"name":"Underground0","currentGameObject":{"instanceID":-58949628},"x":15.0,"y":-0.9195605516433716,"z":2.0}{"name":"Underground0","currentGameObject":{"instanceID":-58949638},"x":15.0,"y":-1.9195605516433716,"z":2.0}{"name":"0","currentGameObject":{"instanceID":-58949648},"x":16.0,"y":1.458991289138794,"z":2.0}{"name":"Underground0","currentGameObject":{"instanceID":-58949668},"x":16.0,"y":0.45899122953414919,"z":2.0}{"name":"Underground0","currentGameObject":{"instanceID":-58949680},"x":16.0,"y":-0.5410087704658508,"z":2.0}{"name":"Underground0","currentGameObject":{"instanceID":-58949690},"x":16.0,"y":-1.541008710861206,"z":2.0}{"name":"0","currentGameObject":{"instanceID":-58949702},"x":17.0,"y":1.291741132736206,"z":2.0}{"name":"Underground0","currentGameObject":{"instanceID":-58949714},"x":17.0,"y":0.29174116253852847,"z":2.0}{"name":"Underground0","currentGameObject":{"instanceID":-58949726},"x":17.0,"y":-0.708258867263794,"z":2.0}{"name":"Underground0","currentGameObject":{"instanceID":-58949738},"x":17.0,"y":-1.708258867263794,"z":2.0}{"name":"0","currentGameObject":{"instanceID":-58949750},"x":18.0,"y":1.0017650127410889,"z":2.0}{"name":"Underground0","currentGameObject":{"instanceID":-58949762},"x":18.0,"y":0.0017650127410888672,"z":2.0}{"name":"Underground0","currentGameObject":{"instanceID":-58949774},"x":18.0,"y":-0.9982349872589111,"z":2.0}{"name":"Underground0","currentGameObject":{"instanceID":-58949784},"x":18.0,"y":-1.9982349872589112,"z":2.0}{"name":"0","currentGameObject":{"instanceID":-58949794},"x":19.0,"y":1.3168184757232667,"z":2.0}{"name":"Underground0","currentGameObject":{"instanceID":-58949814},"x":19.0,"y":0.3168185353279114,"z":2.0}{"name":"Underground0","currentGameObject":{"instanceID":-58949826},"x":19.0,"y":-0.6831814646720886,"z":2.0}{"name":"Underground0","currentGameObject":{"instanceID":-58949836},"x":19.0,"y":-1.6831815242767335,"z":2.0}{"name":"0","currentGameObject":{"instanceID":-58949848},"x":10.0,"y":1.3524478673934937,"z":3.0}{"name":"Underground0","currentGameObject":{"instanceID":-58949860},"x":10.0,"y":0.35244786739349368,"z":3.0}{"name":"Underground0","currentGameObject":{"instanceID":-58949870},"x":10.0,"y":-0.6475521326065064,"z":3.0}{"name":"Underground0","currentGameObject":{"instanceID":-58949882},"x":10.0,"y":-1.6475521326065064,"z":3.0}{"name":"0","currentGameObject":{"instanceID":-58949892},"x":11.0,"y":1.2038921117782593,"z":3.0}{"name":"Underground0","currentGameObject":{"instanceID":-58949904},"x":11.0,"y":0.2038920819759369,"z":3.0}{"name":"Underground0","currentGameObject":{"instanceID":-58949914},"x":11.0,"y":-0.7961078882217407,"z":3.0}{"name":"Underground0","currentGameObject":{"instanceID":-58949924},"x":11.0,"y":-1.7961078882217408,"z":3.0}{"name":"0","currentGameObject":{"instanceID":-58949934},"x":12.0,"y":1.2169288396835328,"z":3.0}{"name":"Underground0","currentGameObject":{"instanceID":-58949946},"x":12.0,"y":0.2169288694858551,"z":3.0}{"name":"Underground0","currentGameObject":{"instanceID":-58949958},"x":12.0,"y":-0.7830711603164673,"z":3.0}{"name":"Underground0","currentGameObject":{"instanceID":-58949970},"x":12.0,"y":-1.7830711603164673,"z":3.0}{"name":"0","currentGameObject":{"instanceID":-58949980},"x":13.0,"y":1.4859627485275269,"z":3.0}{"name":"Underground0","currentGameObject":{"instanceID":-58949992},"x":13.0,"y":0.48596274852752688,"z":3.0}{"name":"Underground0","currentGameObject":{"instanceID":-58950004},"x":13.0,"y":-0.5140372514724731,"z":3.0}{"name":"Underground0","currentGameObject":{"instanceID":-58950016},"x":13.0,"y":-1.5140372514724732,"z":3.0}{"name":"0","currentGameObject":{"instanceID":-58950026},"x":14.0,"y":1.1676464080810547,"z":3.0}{"name":"Underground0","currentGameObject":{"instanceID":-58950038},"x":14.0,"y":0.1676463782787323,"z":3.0}{"name":"Underground0","currentGameObject":{"instanceID":-58950048},"x":14.0,"y":-0.8323535919189453,"z":3.0}{"name":"Underground0","currentGameObject":{"instanceID":-58950058},"x":14.0,"y":-1.8323535919189454,"z":3.0}{"name":"0","currentGameObject":{"instanceID":-58950068},"x":15.0,"y":1.0627069473266602,"z":3.0}{"name":"Underground0","currentGameObject":{"instanceID":-58950080},"x":15.0,"y":0.06270688772201538,"z":3.0}{"name":"Underground0","currentGameObject":{"instanceID":-58950092},"x":15.0,"y":-0.9372931122779846,"z":3.0}{"name":"Underground0","currentGameObject":{"instanceID":-58950102},"x":15.0,"y":-1.9372930526733399,"z":3.0}{"name":"0","currentGameObject":{"instanceID":-58950112},"x":16.0,"y":1.1020257472991944,"z":3.0}{"name":"Underground0","currentGameObject":{"instanceID":-58950124},"x":16.0,"y":0.10202574729919434,"z":3.0}{"name":"Underground0","currentGameObject":{"instanceID":-58950134},"x":16.0,"y":-0.8979742527008057,"z":3.0}{"name":"Underground0","currentGameObject":{"instanceID":-58950146},"x":16.0,"y":-1.8979742527008057,"z":3.0}{"name":"0","currentGameObject":{"instanceID":-58950158},"x":17.0,"y":1.4423754215240479,"z":3.0}{"name":"Underground0","currentGameObject":{"instanceID":-58950170},"x":17.0,"y":0.4423753619194031,"z":3.0}{"name":"Underground0","currentGameObject":{"instanceID":-58950182},"x":17.0,"y":-0.5576246380805969,"z":3.0}{"name":"Underground0","currentGameObject":{"instanceID":-58950194},"x":17.0,"y":-1.5576245784759522,"z":3.0}{"name":"0","currentGameObject":{"instanceID":-58950204},"x":18.0,"y":1.4402337074279786,"z":3.0}{"name":"Underground0","currentGameObject":{"instanceID":-58950216},"x":18.0,"y":0.4402337074279785,"z":3.0}{"name":"Underground0","currentGameObject":{"instanceID":-58950228},"x":18.0,"y":-0.5597662925720215,"z":3.0}{"name":"Underground0","currentGameObject":{"instanceID":-58950238},"x":18.0,"y":-1.5597662925720215,"z":3.0}{"name":"0","currentGameObject":{"instanceID":-58950250},"x":19.0,"y":1.4171950817108155,"z":3.0}{"name":"Underground0","currentGameObject":{"instanceID":-58950262},"x":19.0,"y":0.41719508171081545,"z":3.0}{"name":"Underground0","currentGameObject":{"instanceID":-58950272},"x":19.0,"y":-0.5828049182891846,"z":3.0}{"name":"Underground0","currentGameObject":{"instanceID":-58950284},"x":19.0,"y":-1.5828049182891846,"z":3.0}{"name":"0","currentGameObject":{"instanceID":-58950294},"x":10.0,"y":1.3246653079986573,"z":4.0}{"name":"Underground0","currentGameObject":{"instanceID":-58950306},"x":10.0,"y":0.324665367603302,"z":4.0}{"name":"Underground0","currentGameObject":{"instanceID":-58950318},"x":10.0,"y":-0.675334632396698,"z":4.0}{"name":"Underground0","currentGameObject":{"instanceID":-58950328},"x":10.0,"y":-1.6753346920013428,"z":4.0}{"name":"0","currentGameObject":{"instanceID":-58950340},"x":11.0,"y":1.0359749794006348,"z":4.0}{"name":"Underground0","currentGameObject":{"instanceID":-58950352},"x":11.0,"y":0.03597503900527954,"z":4.0}{"name":"Underground0","currentGameObject":{"instanceID":-58950364},"x":11.0,"y":-0.9640249609947205,"z":4.0}{"name":"Underground0","currentGameObject":{"instanceID":-58950374},"x":11.0,"y":-1.9640250205993653,"z":4.0}{"name":"0","currentGameObject":{"instanceID":-58950386},"x":12.0,"y":1.1470367908477784,"z":4.0}{"name":"Underground0","currentGameObject":{"instanceID":-58950406},"x":12.0,"y":0.14703676104545594,"z":4.0}{"name":"Underground0","currentGameObject":{"instanceID":-58950418},"x":12.0,"y":-0.8529632091522217,"z":4.0}{"name":"Underground0","currentGameObject":{"instanceID":-58950428},"x":12.0,"y":-1.8529632091522217,"z":4.0}{"name":"0","currentGameObject":{"instanceID":-58950438},"x":13.0,"y":1.443373441696167,"z":4.0}{"name":"Underground0","currentGameObject":{"instanceID":-58950450},"x":13.0,"y":0.443373441696167,"z":4.0}{"name":"Underground0","currentGameObject":{"instanceID":-58950460},"x":13.0,"y":-0.556626558303833,"z":4.0}{"name":"Underground0","currentGameObject":{"instanceID":-58950472},"x":13.0,"y":-1.556626558303833,"z":4.0}{"name":"0","currentGameObject":{"instanceID":-58950484},"x":14.0,"y":1.4360811710357667,"z":4.0}{"name":"Underground0","currentGameObject":{"instanceID":-58950496},"x":14.0,"y":0.4360811114311218,"z":4.0}{"name":"Underground0","currentGameObject":{"instanceID":-58950508},"x":14.0,"y":-0.5639188885688782,"z":4.0}{"name":"Underground0","currentGameObject":{"instanceID":-58950518},"x":14.0,"y":-1.5639188289642335,"z":4.0}{"name":"0","currentGameObject":{"instanceID":-58950528},"x":15.0,"y":1.3428802490234376,"z":4.0}{"name":"Underground0","currentGameObject":{"instanceID":-58950540},"x":15.0,"y":0.3428803086280823,"z":4.0}{"name":"Underground0","currentGameObject":{"instanceID":-58950552},"x":15.0,"y":-0.6571196913719177,"z":4.0}{"name":"Underground0","currentGameObject":{"instanceID":-58950562},"x":15.0,"y":-1.6571197509765626,"z":4.0}{"name":"0","currentGameObject":{"instanceID":-58950572},"x":16.0,"y":1.2906584739685059,"z":4.0}{"name":"Underground0","currentGameObject":{"instanceID":-58950584},"x":16.0,"y":0.29065850377082827,"z":4.0}{"name":"Underground0","currentGameObject":{"instanceID":-58950594},"x":16.0,"y":-0.7093415260314941,"z":4.0}{"name":"Underground0","currentGameObject":{"instanceID":-58950604},"x":16.0,"y":-1.7093415260314942,"z":4.0}{"name":"0","currentGameObject":{"instanceID":-58950614},"x":17.0,"y":1.3156261444091797,"z":4.0}{"name":"Underground0","currentGameObject":{"instanceID":-58950626},"x":17.0,"y":0.3156260848045349,"z":4.0}{"name":"Underground0","currentGameObject":{"instanceID":-58950638},"x":17.0,"y":-0.6843739151954651,"z":4.0}{"name":"Underground0","currentGameObject":{"instanceID":-58950648},"x":17.0,"y":-1.6843738555908204,"z":4.0}{"name":"0","currentGameObject":{"instanceID":-58950658},"x":18.0,"y":1.239225149154663,"z":4.0}{"name":"Underground0","currentGameObject":{"instanceID":-58950670},"x":18.0,"y":0.23922517895698548,"z":4.0}{"name":"Underground0","currentGameObject":{"instanceID":-58950682},"x":18.0,"y":-0.7607748508453369,"z":4.0}{"name":"Underground0","currentGameObject":{"instanceID":-58950692},"x":18.0,"y":-1.760774850845337,"z":4.0}{"name":"0","currentGameObject":{"instanceID":-58950702},"x":19.0,"y":1.002500295639038,"z":4.0}{"name":"Underground0","currentGameObject":{"instanceID":-58950714},"x":19.0,"y":0.0025002360343933107,"z":4.0}{"name":"Underground0","currentGameObject":{"instanceID":-58950724},"x":19.0,"y":-0.9974997639656067,"z":4.0}{"name":"Underground0","currentGameObject":{"instanceID":-58950736},"x":19.0,"y":-1.997499704360962,"z":4.0}{"name":"0","currentGameObject":{"instanceID":-58950748},"x":10.0,"y":1.4192700386047364,"z":5.0}{"name":"Underground0","currentGameObject":{"instanceID":-58950760},"x":10.0,"y":0.41927003860473635,"z":5.0}{"name":"Underground0","currentGameObject":{"instanceID":-58950770},"x":10.0,"y":-0.5807299613952637,"z":5.0}{"name":"Underground0","currentGameObject":{"instanceID":-58950782},"x":10.0,"y":-1.5807299613952637,"z":5.0}{"name":"0","currentGameObject":{"instanceID":-58950794},"x":11.0,"y":1.0533599853515626,"z":5.0}{"name":"Underground0","currentGameObject":{"instanceID":-58950806},"x":11.0,"y":0.053359925746917728,"z":5.0}{"name":"Underground0","currentGameObject":{"instanceID":-58950816},"x":11.0,"y":-0.9466400742530823,"z":5.0}{"name":"Underground0","currentGameObject":{"instanceID":-58950826},"x":11.0,"y":-1.9466400146484376,"z":5.0}{"name":"0","currentGameObject":{"instanceID":-58950836},"x":12.0,"y":1.4966425895690919,"z":5.0}{"name":"Underground0","currentGameObject":{"instanceID":-58950848},"x":12.0,"y":0.4966425895690918,"z":5.0}{"name":"Underground0","currentGameObject":{"instanceID":-58950860},"x":12.0,"y":-0.5033574104309082,"z":5.0}{"name":"Underground0","currentGameObject":{"instanceID":-58950870},"x":12.0,"y":-1.5033574104309083,"z":5.0}{"name":"0","currentGameObject":{"instanceID":-58950880},"x":13.0,"y":1.285833477973938,"z":5.0}{"name":"Underground0","currentGameObject":{"instanceID":-58950892},"x":13.0,"y":0.2858334481716156,"z":5.0}{"name":"Underground0","currentGameObject":{"instanceID":-58950902},"x":13.0,"y":-0.714166522026062,"z":5.0}{"name":"Underground0","currentGameObject":{"instanceID":-58950914},"x":13.0,"y":-1.714166522026062,"z":5.0}{"name":"0","currentGameObject":{"instanceID":-58950926},"x":14.0,"y":1.468421220779419,"z":5.0}{"name":"Underground0","currentGameObject":{"instanceID":-58950938},"x":14.0,"y":0.46842122077941897,"z":5.0}{"name":"Underground0","currentGameObject":{"instanceID":-58950948},"x":14.0,"y":-0.531578779220581,"z":5.0}{"name":"Underground0","currentGameObject":{"instanceID":-58950960},"x":14.0,"y":-1.531578779220581,"z":5.0}{"name":"0","currentGameObject":{"instanceID":-58950970},"x":15.0,"y":1.1835235357284547,"z":5.0}{"name":"Underground0","currentGameObject":{"instanceID":-58950982},"x":15.0,"y":0.18352356553077699,"z":5.0}{"name":"Underground0","currentGameObject":{"instanceID":-58950994},"x":15.0,"y":-0.8164764642715454,"z":5.0}{"name":"Underground0","currentGameObject":{"instanceID":-58951006},"x":15.0,"y":-1.8164764642715455,"z":5.0}{"name":"0","currentGameObject":{"instanceID":-58951016},"x":16.0,"y":1.0203168392181397,"z":5.0}{"name":"Underground0","currentGameObject":{"instanceID":-58951028},"x":16.0,"y":0.020316898822784425,"z":5.0}{"name":"Underground0","currentGameObject":{"instanceID":-58951038},"x":16.0,"y":-0.9796831011772156,"z":5.0}{"name":"Underground0","currentGameObject":{"instanceID":-58951050},"x":16.0,"y":-1.9796831607818604,"z":5.0}{"name":"0","currentGameObject":{"instanceID":-58951060},"x":17.0,"y":1.4305622577667237,"z":5.0}{"name":"Underground0","currentGameObject":{"instanceID":-58951072},"x":17.0,"y":0.4305623173713684,"z":5.0}{"name":"Underground0","currentGameObject":{"instanceID":-58951084},"x":17.0,"y":-0.5694376826286316,"z":5.0}{"name":"Underground0","currentGameObject":{"instanceID":-58951096},"x":17.0,"y":-1.5694377422332764,"z":5.0}{"name":"0","currentGameObject":{"instanceID":-58951106},"x":18.0,"y":1.36283540725708,"z":5.0}{"name":"Underground0","currentGameObject":{"instanceID":-58951126},"x":18.0,"y":0.3628353476524353,"z":5.0}{"name":"Underground0","currentGameObject":{"instanceID":-58951136},"x":18.0,"y":-0.6371646523475647,"z":5.0}{"name":"Underground0","currentGameObject":{"instanceID":-58951148},"x":18.0,"y":-1.63716459274292,"z":5.0}{"name":"0","currentGameObject":{"instanceID":-58951160},"x":19.0,"y":1.3788905143737794,"z":5.0}{"name":"Underground0","currentGameObject":{"instanceID":-58951172},"x":19.0,"y":0.3788904547691345,"z":5.0}{"name":"Underground0","currentGameObject":{"instanceID":-58951182},"x":19.0,"y":-0.6211095452308655,"z":5.0}{"name":"Underground0","currentGameObject":{"instanceID":-58951194},"x":19.0,"y":-1.6211094856262208,"z":5.0}{"name":"0","currentGameObject":{"instanceID":-58951206},"x":10.0,"y":1.360126256942749,"z":6.0}{"name":"Underground0","currentGameObject":{"instanceID":-58951226},"x":10.0,"y":0.3601263165473938,"z":6.0}{"name":"Underground0","currentGameObject":{"instanceID":-58951238},"x":10.0,"y":-0.6398736834526062,"z":6.0}{"name":"Underground0","currentGameObject":{"instanceID":-58951250},"x":10.0,"y":-1.639873743057251,"z":6.0}{"name":"0","currentGameObject":{"instanceID":-58951260},"x":11.0,"y":1.164031744003296,"z":6.0}{"name":"Underground0","currentGameObject":{"instanceID":-58951272},"x":11.0,"y":0.1640317142009735,"z":6.0}{"name":"Underground0","currentGameObject":{"instanceID":-58951284},"x":11.0,"y":-0.8359682559967041,"z":6.0}{"name":"Underground0","currentGameObject":{"instanceID":-58951294},"x":11.0,"y":-1.835968255996704,"z":6.0}{"name":"0","currentGameObject":{"instanceID":-58951304},"x":12.0,"y":1.1198549270629883,"z":6.0}{"name":"Underground0","currentGameObject":{"instanceID":-58951316},"x":12.0,"y":0.11985498666763306,"z":6.0}{"name":"Underground0","currentGameObject":{"instanceID":-58951328},"x":12.0,"y":-0.8801450133323669,"z":6.0}{"name":"Underground0","currentGameObject":{"instanceID":-58951340},"x":12.0,"y":-1.8801450729370118,"z":6.0}{"name":"0","currentGameObject":{"instanceID":-58951350},"x":13.0,"y":1.393449068069458,"z":6.0}{"name":"Underground0","currentGameObject":{"instanceID":-58951362},"x":13.0,"y":0.3934491276741028,"z":6.0}{"name":"Underground0","currentGameObject":{"instanceID":-58951374},"x":13.0,"y":-0.6065508723258972,"z":6.0}{"name":"Underground0","currentGameObject":{"instanceID":-58951386},"x":13.0,"y":-1.606550931930542,"z":6.0}{"name":"0","currentGameObject":{"instanceID":-58951398},"x":14.0,"y":1.4502713680267335,"z":6.0}{"name":"Underground0","currentGameObject":{"instanceID":-58951410},"x":14.0,"y":0.4502714276313782,"z":6.0}{"name":"Underground0","currentGameObject":{"instanceID":-58951420},"x":14.0,"y":-0.5497285723686218,"z":6.0}{"name":"Underground0","currentGameObject":{"instanceID":-58951432},"x":14.0,"y":-1.5497286319732667,"z":6.0}{"name":"0","currentGameObject":{"instanceID":-58951442},"x":15.0,"y":1.4285187721252442,"z":6.0}{"name":"Underground0","currentGameObject":{"instanceID":-58951454},"x":15.0,"y":0.4285188317298889,"z":6.0}{"name":"Underground0","currentGameObject":{"instanceID":-58951464},"x":15.0,"y":-0.5714811682701111,"z":6.0}{"name":"Underground0","currentGameObject":{"instanceID":-58951474},"x":15.0,"y":-1.5714812278747559,"z":6.0}{"name":"0","currentGameObject":{"instanceID":-58951484},"x":16.0,"y":1.1242033243179322,"z":6.0}{"name":"Underground0","currentGameObject":{"instanceID":-58951496},"x":16.0,"y":0.12420332431793213,"z":6.0}{"name":"Underground0","currentGameObject":{"instanceID":-58951506},"x":16.0,"y":-0.8757966756820679,"z":6.0}{"name":"Underground0","currentGameObject":{"instanceID":-58951518},"x":16.0,"y":-1.8757966756820679,"z":6.0}{"name":"0","currentGameObject":{"instanceID":-58951528},"x":17.0,"y":1.3586125373840333,"z":6.0}{"name":"Underground0","currentGameObject":{"instanceID":-58951540},"x":17.0,"y":0.35861247777938845,"z":6.0}{"name":"Underground0","currentGameObject":{"instanceID":-58951550},"x":17.0,"y":-0.6413875222206116,"z":6.0}{"name":"Underground0","currentGameObject":{"instanceID":-58951560},"x":17.0,"y":-1.6413874626159669,"z":6.0}{"name":"0","currentGameObject":{"instanceID":-58951572},"x":18.0,"y":1.2764062881469727,"z":6.0}{"name":"Underground0","currentGameObject":{"instanceID":-58951584},"x":18.0,"y":0.27640631794929507,"z":6.0}{"name":"Underground0","currentGameObject":{"instanceID":-58951596},"x":18.0,"y":-0.7235937118530273,"z":6.0}{"name":"Underground0","currentGameObject":{"instanceID":-58951608},"x":18.0,"y":-1.7235937118530274,"z":6.0}{"name":"0","currentGameObject":{"instanceID":-58951620},"x":19.0,"y":1.0908114910125733,"z":6.0}{"name":"Underground0","currentGameObject":{"instanceID":-58951632},"x":19.0,"y":0.09081155061721802,"z":6.0}{"name":"Underground0","currentGameObject":{"instanceID":-58951644},"x":19.0,"y":-0.909188449382782,"z":6.0}{"name":"Underground0","currentGameObject":{"instanceID":-58951656},"x":19.0,"y":-1.9091885089874268,"z":6.0}{"name":"0","currentGameObject":{"instanceID":-58951666},"x":10.0,"y":1.2936517000198365,"z":7.0}{"name":"Underground0","currentGameObject":{"instanceID":-58951678},"x":10.0,"y":0.2936517298221588,"z":7.0}{"name":"Underground0","currentGameObject":{"instanceID":-58951690},"x":10.0,"y":-0.7063482999801636,"z":7.0}{"name":"Underground0","currentGameObject":{"instanceID":-58951702},"x":10.0,"y":-1.7063482999801636,"z":7.0}{"name":"0","currentGameObject":{"instanceID":-58951714},"x":11.0,"y":1.1647694110870362,"z":7.0}{"name":"Underground0","currentGameObject":{"instanceID":-58951734},"x":11.0,"y":0.16476938128471375,"z":7.0}{"name":"Underground0","currentGameObject":{"instanceID":-58951744},"x":11.0,"y":-0.8352305889129639,"z":7.0}{"name":"Underground0","currentGameObject":{"instanceID":-58951754},"x":11.0,"y":-1.8352305889129639,"z":7.0}{"name":"0","currentGameObject":{"instanceID":-58951764},"x":12.0,"y":1.1821831464767457,"z":7.0}{"name":"Underground0","currentGameObject":{"instanceID":-58951776},"x":12.0,"y":0.182183176279068,"z":7.0}{"name":"Underground0","currentGameObject":{"instanceID":-58951788},"x":12.0,"y":-0.8178168535232544,"z":7.0}{"name":"Underground0","currentGameObject":{"instanceID":-58951798},"x":12.0,"y":-1.8178168535232545,"z":7.0}{"name":"0","currentGameObject":{"instanceID":-58951808},"x":13.0,"y":1.1363592147827149,"z":7.0}{"name":"Underground0","currentGameObject":{"instanceID":-58951820},"x":13.0,"y":0.13635918498039246,"z":7.0}{"name":"Underground0","currentGameObject":{"instanceID":-58951832},"x":13.0,"y":-0.8636407852172852,"z":7.0}{"name":"Underground0","currentGameObject":{"instanceID":-58951844},"x":13.0,"y":-1.8636407852172852,"z":7.0}{"name":"0","currentGameObject":{"instanceID":-58951854},"x":14.0,"y":1.0158510208129883,"z":7.0}{"name":"Underground0","currentGameObject":{"instanceID":-58951866},"x":14.0,"y":0.01585102081298828,"z":7.0}{"name":"Underground0","currentGameObject":{"instanceID":-58951876},"x":14.0,"y":-0.9841489791870117,"z":7.0}{"name":"Underground0","currentGameObject":{"instanceID":-58951888},"x":14.0,"y":-1.9841489791870118,"z":7.0}{"name":"0","currentGameObject":{"instanceID":-58951900},"x":15.0,"y":1.2886009216308594,"z":7.0}{"name":"Underground0","currentGameObject":{"instanceID":-58951912},"x":15.0,"y":0.28860095143318179,"z":7.0}{"name":"Underground0","currentGameObject":{"instanceID":-58951924},"x":15.0,"y":-0.7113990783691406,"z":7.0}{"name":"Underground0","currentGameObject":{"instanceID":-58951936},"x":15.0,"y":-1.7113990783691407,"z":7.0}{"name":"0","currentGameObject":{"instanceID":-58951946},"x":16.0,"y":1.2726019620895386,"z":7.0}{"name":"Underground0","currentGameObject":{"instanceID":-58951958},"x":16.0,"y":0.2726019322872162,"z":7.0}{"name":"Underground0","currentGameObject":{"instanceID":-58951970},"x":16.0,"y":-0.7273980379104614,"z":7.0}{"name":"Underground0","currentGameObject":{"instanceID":-58951980},"x":16.0,"y":-1.7273980379104615,"z":7.0}{"name":"0","currentGameObject":{"instanceID":-58951990},"x":17.0,"y":1.22487211227417,"z":7.0}{"name":"Underground0","currentGameObject":{"instanceID":-58952002},"x":17.0,"y":0.22487208247184754,"z":7.0}{"name":"Underground0","currentGameObject":{"instanceID":-58952012},"x":17.0,"y":-0.7751278877258301,"z":7.0}{"name":"Underground0","currentGameObject":{"instanceID":-58952024},"x":17.0,"y":-1.77512788772583,"z":7.0}{"name":"0","currentGameObject":{"instanceID":-58952034},"x":18.0,"y":1.4586644172668458,"z":7.0}{"name":"Underground0","currentGameObject":{"instanceID":-58952046},"x":18.0,"y":0.45866435766220095,"z":7.0}{"name":"Underground0","currentGameObject":{"instanceID":-58952058},"x":18.0,"y":-0.5413356423377991,"z":7.0}{"name":"Underground0","currentGameObject":{"instanceID":-58952070},"x":18.0,"y":-1.5413355827331544,"z":7.0}{"name":"0","currentGameObject":{"instanceID":-58952082},"x":19.0,"y":1.3064944744110108,"z":7.0}{"name":"Underground0","currentGameObject":{"instanceID":-58952094},"x":19.0,"y":0.30649444460868838,"z":7.0}{"name":"Underground0","currentGameObject":{"instanceID":-58952106},"x":19.0,"y":-0.6935055255889893,"z":7.0}{"name":"Underground0","currentGameObject":{"instanceID":-58952118},"x":19.0,"y":-1.6935055255889893,"z":7.0}{"name":"0","currentGameObject":{"instanceID":-58952130},"x":10.0,"y":1.0443146228790284,"z":8.0}{"name":"Underground0","currentGameObject":{"instanceID":-58952142},"x":10.0,"y":0.044314682483673099,"z":8.0}{"name":"Underground0","currentGameObject":{"instanceID":-58952152},"x":10.0,"y":-0.9556853175163269,"z":8.0}{"name":"Underground0","currentGameObject":{"instanceID":-58952164},"x":10.0,"y":-1.9556853771209717,"z":8.0}{"name":"0","currentGameObject":{"instanceID":-58952176},"x":11.0,"y":1.4436672925949097,"z":8.0}{"name":"Underground0","currentGameObject":{"instanceID":-58952188},"x":11.0,"y":0.44366729259490969,"z":8.0}{"name":"Underground0","currentGameObject":{"instanceID":-58952198},"x":11.0,"y":-0.5563327074050903,"z":8.0}{"name":"Underground0","currentGameObject":{"instanceID":-58952210},"x":11.0,"y":-1.5563327074050904,"z":8.0}{"name":"0","currentGameObject":{"instanceID":-58952222},"x":12.0,"y":1.4307513236999512,"z":8.0}{"name":"Underground0","currentGameObject":{"instanceID":-58952234},"x":12.0,"y":0.43075132369995119,"z":8.0}{"name":"Underground0","currentGameObject":{"instanceID":-58952244},"x":12.0,"y":-0.5692486763000488,"z":8.0}{"name":"Underground0","currentGameObject":{"instanceID":-58952256},"x":12.0,"y":-1.5692486763000489,"z":8.0}{"name":"0","currentGameObject":{"instanceID":-58952268},"x":13.0,"y":1.2086834907531739,"z":8.0}{"name":"Underground0","currentGameObject":{"instanceID":-58952280},"x":13.0,"y":0.20868352055549622,"z":8.0}{"name":"Underground0","currentGameObject":{"instanceID":-58952290},"x":13.0,"y":-0.7913165092468262,"z":8.0}{"name":"Underground0","currentGameObject":{"instanceID":-58952302},"x":13.0,"y":-1.7913165092468262,"z":8.0}{"name":"0","currentGameObject":{"instanceID":-58952314},"x":14.0,"y":1.419708490371704,"z":8.0}{"name":"Underground0","currentGameObject":{"instanceID":-58952334},"x":14.0,"y":0.4197084903717041,"z":8.0}{"name":"Underground0","currentGameObject":{"instanceID":-58952344},"x":14.0,"y":-0.5802915096282959,"z":8.0}{"name":"Underground0","currentGameObject":{"instanceID":-58952356},"x":14.0,"y":-1.580291509628296,"z":8.0}{"name":"0","currentGameObject":{"instanceID":-58952366},"x":15.0,"y":1.4900052547454835,"z":8.0}{"name":"Underground0","currentGameObject":{"instanceID":-58952378},"x":15.0,"y":0.4900051951408386,"z":8.0}{"name":"Underground0","currentGameObject":{"instanceID":-58952390},"x":15.0,"y":-0.5099948048591614,"z":8.0}{"name":"Underground0","currentGameObject":{"instanceID":-58952400},"x":15.0,"y":-1.5099947452545167,"z":8.0}{"name":"0","currentGameObject":{"instanceID":-58952410},"x":16.0,"y":1.2288169860839844,"z":8.0}{"name":"Underground0","currentGameObject":{"instanceID":-58952422},"x":16.0,"y":0.228816956281662,"z":8.0}{"name":"Underground0","currentGameObject":{"instanceID":-58952432},"x":16.0,"y":-0.7711830139160156,"z":8.0}{"name":"Underground0","currentGameObject":{"instanceID":-58952442},"x":16.0,"y":-1.7711830139160157,"z":8.0}{"name":"0","currentGameObject":{"instanceID":-58952452},"x":17.0,"y":1.1625901460647584,"z":8.0}{"name":"Underground0","currentGameObject":{"instanceID":-58952464},"x":17.0,"y":0.1625901162624359,"z":8.0}{"name":"Underground0","currentGameObject":{"instanceID":-58952474},"x":17.0,"y":-0.8374098539352417,"z":8.0}{"name":"Underground0","currentGameObject":{"instanceID":-58952484},"x":17.0,"y":-1.8374098539352418,"z":8.0}{"name":"0","currentGameObject":{"instanceID":-58952496},"x":18.0,"y":1.1960092782974244,"z":8.0}{"name":"Underground0","currentGameObject":{"instanceID":-58952508},"x":18.0,"y":0.19600924849510194,"z":8.0}{"name":"Underground0","currentGameObject":{"instanceID":-58952520},"x":18.0,"y":-0.8039907217025757,"z":8.0}{"name":"Underground0","currentGameObject":{"instanceID":-58952530},"x":18.0,"y":-1.8039907217025757,"z":8.0}{"name":"0","currentGameObject":{"instanceID":-58952542},"x":19.0,"y":1.3689128160476685,"z":8.0}{"name":"Underground0","currentGameObject":{"instanceID":-58952554},"x":19.0,"y":0.36891281604766848,"z":8.0}{"name":"Underground0","currentGameObject":{"instanceID":-58952564},"x":19.0,"y":-0.6310871839523315,"z":8.0}{"name":"Underground0","currentGameObject":{"instanceID":-58952574},"x":19.0,"y":-1.6310871839523316,"z":8.0}{"name":"0","currentGameObject":{"instanceID":-58952584},"x":10.0,"y":1.3978986740112305,"z":9.0}{"name":"Underground0","currentGameObject":{"instanceID":-58952604},"x":10.0,"y":0.3978986144065857,"z":9.0}{"name":"Underground0","currentGameObject":{"instanceID":-58952614},"x":10.0,"y":-0.6021013855934143,"z":9.0}{"name":"Underground0","currentGameObject":{"instanceID":-58952624},"x":10.0,"y":-1.6021013259887696,"z":9.0}{"name":"0","currentGameObject":{"instanceID":-58952636},"x":11.0,"y":1.321314811706543,"z":9.0}{"name":"Underground0","currentGameObject":{"instanceID":-58952648},"x":11.0,"y":0.3213147521018982,"z":9.0}{"name":"Underground0","currentGameObject":{"instanceID":-58952660},"x":11.0,"y":-0.6786852478981018,"z":9.0}{"name":"Underground0","currentGameObject":{"instanceID":-58952672},"x":11.0,"y":-1.678685188293457,"z":9.0}{"name":"0","currentGameObject":{"instanceID":-58952684},"x":12.0,"y":1.196732997894287,"z":9.0}{"name":"Underground0","currentGameObject":{"instanceID":-58952696},"x":12.0,"y":0.1967330276966095,"z":9.0}{"name":"Underground0","currentGameObject":{"instanceID":-58952706},"x":12.0,"y":-0.8032670021057129,"z":9.0}{"name":"Underground0","currentGameObject":{"instanceID":-58952718},"x":12.0,"y":-1.803267002105713,"z":9.0}{"name":"0","currentGameObject":{"instanceID":-58952728},"x":13.0,"y":1.037654995918274,"z":9.0}{"name":"Underground0","currentGameObject":{"instanceID":-58952740},"x":13.0,"y":0.037654995918273929,"z":9.0}{"name":"Underground0","currentGameObject":{"instanceID":-58952750},"x":13.0,"y":-0.9623450040817261,"z":9.0}{"name":"Underground0","currentGameObject":{"instanceID":-58952762},"x":13.0,"y":-1.962345004081726,"z":9.0}{"name":"0","currentGameObject":{"instanceID":-58952774},"x":14.0,"y":1.3579254150390626,"z":9.0}{"name":"Underground0","currentGameObject":{"instanceID":-58952786},"x":14.0,"y":0.3579254150390625,"z":9.0}{"name":"Underground0","currentGameObject":{"instanceID":-58952798},"x":14.0,"y":-0.6420745849609375,"z":9.0}{"name":"Underground0","currentGameObject":{"instanceID":-58952810},"x":14.0,"y":-1.6420745849609376,"z":9.0}{"name":"0","currentGameObject":{"instanceID":-58952822},"x":15.0,"y":1.005016565322876,"z":9.0}{"name":"Underground0","currentGameObject":{"instanceID":-58952834},"x":15.0,"y":0.005016505718231201,"z":9.0}{"name":"Underground0","currentGameObject":{"instanceID":-58952844},"x":15.0,"y":-0.9949834942817688,"z":9.0}{"name":"Underground0","currentGameObject":{"instanceID":-58952856},"x":15.0,"y":-1.994983434677124,"z":9.0}{"name":"0","currentGameObject":{"instanceID":-58952868},"x":16.0,"y":1.4869731664657593,"z":9.0}{"name":"Underground0","currentGameObject":{"instanceID":-58952880},"x":16.0,"y":0.4869731664657593,"z":9.0}{"name":"Underground0","currentGameObject":{"instanceID":-58952892},"x":16.0,"y":-0.5130268335342407,"z":9.0}{"name":"Underground0","currentGameObject":{"instanceID":-58952904},"x":16.0,"y":-1.5130268335342408,"z":9.0}{"name":"0","currentGameObject":{"instanceID":-58952914},"x":17.0,"y":1.444507360458374,"z":9.0}{"name":"Underground0","currentGameObject":{"instanceID":-58952926},"x":17.0,"y":0.44450730085372927,"z":9.0}{"name":"Underground0","currentGameObject":{"instanceID":-58952938},"x":17.0,"y":-0.5554926991462708,"z":9.0}{"name":"Underground0","currentGameObject":{"instanceID":-58952950},"x":17.0,"y":-1.555492639541626,"z":9.0}{"name":"0","currentGameObject":{"instanceID":-58952962},"x":18.0,"y":1.228816032409668,"z":9.0}{"name":"Underground0","currentGameObject":{"instanceID":-58952982},"x":18.0,"y":0.22881600260734559,"z":9.0}{"name":"Underground0","currentGameObject":{"instanceID":-58952994},"x":18.0,"y":-0.771183967590332,"z":9.0}{"name":"Underground0","currentGameObject":{"instanceID":-58953004},"x":18.0,"y":-1.771183967590332,"z":9.0}{"name":"0","currentGameObject":{"instanceID":-58953016},"x":19.0,"y":1.1009447574615479,"z":9.0}{"name":"Underground0","currentGameObject":{"instanceID":-58953028},"x":19.0,"y":0.10094469785690308,"z":9.0}{"name":"Underground0","currentGameObject":{"instanceID":-58953040},"x":19.0,"y":-0.8990553021430969,"z":9.0}{"name":"Underground0","currentGameObject":{"instanceID":-58953052},"x":19.0,"y":-1.8990552425384522,"z":9.0}{"name":"0","currentGameObject":{"instanceID":-58953062},"x":10.0,"y":1.2449504137039185,"z":10.0}{"name":"Underground0","currentGameObject":{"instanceID":-58953074},"x":10.0,"y":0.24495044350624085,"z":10.0}{"name":"Underground0","currentGameObject":{"instanceID":-58953084},"x":10.0,"y":-0.7550495862960815,"z":10.0}{"name":"Underground0","currentGameObject":{"instanceID":-58953096},"x":10.0,"y":-1.7550495862960816,"z":10.0}{"name":"0","currentGameObject":{"instanceID":-58953108},"x":11.0,"y":1.43101167678833,"z":10.0}{"name":"Underground0","currentGameObject":{"instanceID":-58953120},"x":11.0,"y":0.4310116767883301,"z":10.0}{"name":"Underground0","currentGameObject":{"instanceID":-58953130},"x":11.0,"y":-0.5689883232116699,"z":10.0}{"name":"Underground0","currentGameObject":{"instanceID":-58953140},"x":11.0,"y":-1.56898832321167,"z":10.0}{"name":"0","currentGameObject":{"instanceID":-58953150},"x":12.0,"y":1.057990312576294,"z":10.0}{"name":"Underground0","currentGameObject":{"instanceID":-58953162},"x":12.0,"y":0.057990312576293948,"z":10.0}{"name":"Underground0","currentGameObject":{"instanceID":-58953174},"x":12.0,"y":-0.942009687423706,"z":10.0}{"name":"Underground0","currentGameObject":{"instanceID":-58953184},"x":12.0,"y":-1.942009687423706,"z":10.0}{"name":"0","currentGameObject":{"instanceID":-58953194},"x":13.0,"y":1.477223515510559,"z":10.0}{"name":"Underground0","currentGameObject":{"instanceID":-58953214},"x":13.0,"y":0.4772235155105591,"z":10.0}{"name":"Underground0","currentGameObject":{"instanceID":-58953226},"x":13.0,"y":-0.5227764844894409,"z":10.0}{"name":"Underground0","currentGameObject":{"instanceID":-58953238},"x":13.0,"y":-1.522776484489441,"z":10.0}{"name":"0","currentGameObject":{"instanceID":-58953250},"x":14.0,"y":1.3850873708724976,"z":10.0}{"name":"Underground0","currentGameObject":{"instanceID":-58953270},"x":14.0,"y":0.38508737087249758,"z":10.0}{"name":"Underground0","currentGameObject":{"instanceID":-58953280},"x":14.0,"y":-0.6149126291275024,"z":10.0}{"name":"Underground0","currentGameObject":{"instanceID":-58953290},"x":14.0,"y":-1.6149126291275025,"z":10.0}{"name":"0","currentGameObject":{"instanceID":-58953302},"x":15.0,"y":1.0763404369354249,"z":10.0}{"name":"Underground0","currentGameObject":{"instanceID":-58953314},"x":15.0,"y":0.0763404369354248,"z":10.0}{"name":"Underground0","currentGameObject":{"instanceID":-58953324},"x":15.0,"y":-0.9236595630645752,"z":10.0}{"name":"Underground0","currentGameObject":{"instanceID":-58953336},"x":15.0,"y":-1.9236595630645753,"z":10.0}{"name":"0","currentGameObject":{"instanceID":-58953348},"x":16.0,"y":1.0880465507507325,"z":10.0}{"name":"Underground0","currentGameObject":{"instanceID":-58953360},"x":16.0,"y":0.0880466103553772,"z":10.0}{"name":"Underground0","currentGameObject":{"instanceID":-58953372},"x":16.0,"y":-0.9119533896446228,"z":10.0}{"name":"Underground0","currentGameObject":{"instanceID":-58953382},"x":16.0,"y":-1.9119534492492676,"z":10.0}{"name":"0","currentGameObject":{"instanceID":-58953392},"x":17.0,"y":1.3446404933929444,"z":10.0}{"name":"Underground0","currentGameObject":{"instanceID":-58953404},"x":17.0,"y":0.34464043378829958,"z":10.0}{"name":"Underground0","currentGameObject":{"instanceID":-58953416},"x":17.0,"y":-0.6553595662117004,"z":10.0}{"name":"Underground0","currentGameObject":{"instanceID":-58953426},"x":17.0,"y":-1.6553595066070557,"z":10.0}{"name":"0","currentGameObject":{"instanceID":-58953436},"x":18.0,"y":1.4668080806732178,"z":10.0}{"name":"Underground0","currentGameObject":{"instanceID":-58953456},"x":18.0,"y":0.46680814027786257,"z":10.0}{"name":"Underground0","currentGameObject":{"instanceID":-58953468},"x":18.0,"y":-0.5331918597221375,"z":10.0}{"name":"Underground0","currentGameObject":{"instanceID":-58953478},"x":18.0,"y":-1.5331919193267823,"z":10.0}{"name":"0","currentGameObject":{"instanceID":-58953488},"x":19.0,"y":1.1556766033172608,"z":10.0}{"name":"Underground0","currentGameObject":{"instanceID":-58953500},"x":19.0,"y":0.15567657351493836,"z":10.0}{"name":"Underground0","currentGameObject":{"instanceID":-58953512},"x":19.0,"y":-0.8443233966827393,"z":10.0}{"name":"Underground0","currentGameObject":{"instanceID":-58953524},"x":19.0,"y":-1.8443233966827393,"z":10.0}