{"name":"3","currentGameObject":{"instanceID":-393122},"x":10.0,"y":1.4569940567016602,"z":31.0}{"name":"Underground3","currentGameObject":{"instanceID":-393134},"x":10.0,"y":0.4569939970970154,"z":31.0}{"name":"Underground3","currentGameObject":{"instanceID":-393144},"x":10.0,"y":-0.5430060029029846,"z":31.0}{"name":"Underground3","currentGameObject":{"instanceID":-393156},"x":10.0,"y":-1.5430059432983399,"z":31.0}{"name":"3","currentGameObject":{"instanceID":-393166},"x":11.0,"y":1.131935715675354,"z":31.0}{"name":"Underground3","currentGameObject":{"instanceID":-393178},"x":11.0,"y":0.1319357454776764,"z":31.0}{"name":"Underground3","currentGameObject":{"instanceID":-393188},"x":11.0,"y":-0.868064284324646,"z":31.0}{"name":"Underground3","currentGameObject":{"instanceID":-393198},"x":11.0,"y":-1.868064284324646,"z":31.0}{"name":"3","currentGameObject":{"instanceID":-393208},"x":12.0,"y":1.2928482294082642,"z":31.0}{"name":"Underground3","currentGameObject":{"instanceID":-393220},"x":12.0,"y":0.2928481996059418,"z":31.0}{"name":"Underground3","currentGameObject":{"instanceID":-393230},"x":12.0,"y":-0.7071517705917358,"z":31.0}{"name":"Underground3","currentGameObject":{"instanceID":-393242},"x":12.0,"y":-1.7071517705917359,"z":31.0}{"name":"3","currentGameObject":{"instanceID":-393254},"x":13.0,"y":1.2725824117660523,"z":31.0}{"name":"Underground3","currentGameObject":{"instanceID":-393266},"x":13.0,"y":0.27258244156837466,"z":31.0}{"name":"Underground3","currentGameObject":{"instanceID":-393276},"x":13.0,"y":-0.7274175882339478,"z":31.0}{"name":"Underground3","currentGameObject":{"instanceID":-393286},"x":13.0,"y":-1.7274175882339478,"z":31.0}{"name":"3","currentGameObject":{"instanceID":-393296},"x":14.0,"y":1.3122854232788087,"z":31.0}{"name":"Underground3","currentGameObject":{"instanceID":-393308},"x":14.0,"y":0.312285453081131,"z":31.0}{"name":"Underground3","currentGameObject":{"instanceID":-393320},"x":14.0,"y":-0.6877145767211914,"z":31.0}{"name":"Underground3","currentGameObject":{"instanceID":-393332},"x":14.0,"y":-1.6877145767211915,"z":31.0}{"name":"3","currentGameObject":{"instanceID":-393344},"x":15.0,"y":1.4165802001953126,"z":31.0}{"name":"Underground3","currentGameObject":{"instanceID":-393356},"x":15.0,"y":0.4165802597999573,"z":31.0}{"name":"Underground3","currentGameObject":{"instanceID":-393368},"x":15.0,"y":-0.5834197402000427,"z":31.0}{"name":"Underground3","currentGameObject":{"instanceID":-393380},"x":15.0,"y":-1.5834197998046876,"z":31.0}{"name":"3","currentGameObject":{"instanceID":-393392},"x":16.0,"y":1.2245880365371705,"z":31.0}{"name":"Underground3","currentGameObject":{"instanceID":-393404},"x":16.0,"y":0.2245880663394928,"z":31.0}{"name":"Underground3","currentGameObject":{"instanceID":-393414},"x":16.0,"y":-0.7754119634628296,"z":31.0}{"name":"Underground3","currentGameObject":{"instanceID":-393426},"x":16.0,"y":-1.7754119634628297,"z":31.0}{"name":"3","currentGameObject":{"instanceID":-393436},"x":17.0,"y":1.0301986932754517,"z":31.0}{"name":"Underground3","currentGameObject":{"instanceID":-393456},"x":17.0,"y":0.03019869327545166,"z":31.0}{"name":"Underground3","currentGameObject":{"instanceID":-393466},"x":17.0,"y":-0.9698013067245483,"z":31.0}{"name":"Underground3","currentGameObject":{"instanceID":-393478},"x":17.0,"y":-1.9698013067245484,"z":31.0}{"name":"3","currentGameObject":{"instanceID":-393490},"x":18.0,"y":1.0429458618164063,"z":31.0}{"name":"Underground3","currentGameObject":{"instanceID":-393502},"x":18.0,"y":0.04294586181640625,"z":31.0}{"name":"Underground3","currentGameObject":{"instanceID":-393512},"x":18.0,"y":-0.9570541381835938,"z":31.0}{"name":"Underground3","currentGameObject":{"instanceID":-393524},"x":18.0,"y":-1.9570541381835938,"z":31.0}{"name":"3","currentGameObject":{"instanceID":-393536},"x":19.0,"y":1.2254458665847779,"z":31.0}{"name":"Underground3","currentGameObject":{"instanceID":-393548},"x":19.0,"y":0.22544583678245545,"z":31.0}{"name":"Underground3","currentGameObject":{"instanceID":-393560},"x":19.0,"y":-0.7745541334152222,"z":31.0}{"name":"Underground3","currentGameObject":{"instanceID":-393572},"x":19.0,"y":-1.7745541334152222,"z":31.0}{"name":"3","currentGameObject":{"instanceID":-393584},"x":10.0,"y":1.2094511985778809,"z":32.0}{"name":"Underground3","currentGameObject":{"instanceID":-393596},"x":10.0,"y":0.20945116877555848,"z":32.0}{"name":"Underground3","currentGameObject":{"instanceID":-393606},"x":10.0,"y":-0.7905488014221191,"z":32.0}{"name":"Underground3","currentGameObject":{"instanceID":-393618},"x":10.0,"y":-1.7905488014221192,"z":32.0}{"name":"3","currentGameObject":{"instanceID":-393630},"x":11.0,"y":1.110260009765625,"z":32.0}{"name":"Underground3","currentGameObject":{"instanceID":-393650},"x":11.0,"y":0.11025995016098023,"z":32.0}{"name":"Underground3","currentGameObject":{"instanceID":-393662},"x":11.0,"y":-0.8897400498390198,"z":32.0}{"name":"Underground3","currentGameObject":{"instanceID":-393672},"x":11.0,"y":-1.889739990234375,"z":32.0}{"name":"3","currentGameObject":{"instanceID":-393684},"x":12.0,"y":1.0602065324783326,"z":32.0}{"name":"Underground3","currentGameObject":{"instanceID":-393704},"x":12.0,"y":0.06020653247833252,"z":32.0}{"name":"Underground3","currentGameObject":{"instanceID":-393716},"x":12.0,"y":-0.9397934675216675,"z":32.0}{"name":"Underground3","currentGameObject":{"instanceID":-393728},"x":12.0,"y":-1.9397934675216675,"z":32.0}{"name":"3","currentGameObject":{"instanceID":-393738},"x":13.0,"y":1.2363015413284302,"z":32.0}{"name":"Underground3","currentGameObject":{"instanceID":-393750},"x":13.0,"y":0.23630157113075257,"z":32.0}{"name":"Underground3","currentGameObject":{"instanceID":-393760},"x":13.0,"y":-0.7636984586715698,"z":32.0}{"name":"Underground3","currentGameObject":{"instanceID":-393770},"x":13.0,"y":-1.7636984586715699,"z":32.0}{"name":"3","currentGameObject":{"instanceID":-393782},"x":14.0,"y":1.4824681282043458,"z":32.0}{"name":"Underground3","currentGameObject":{"instanceID":-393802},"x":14.0,"y":0.4824681282043457,"z":32.0}{"name":"Underground3","currentGameObject":{"instanceID":-393814},"x":14.0,"y":-0.5175318717956543,"z":32.0}{"name":"Underground3","currentGameObject":{"instanceID":-393824},"x":14.0,"y":-1.5175318717956544,"z":32.0}{"name":"3","currentGameObject":{"instanceID":-393836},"x":15.0,"y":1.3239617347717286,"z":32.0}{"name":"Underground3","currentGameObject":{"instanceID":-393848},"x":15.0,"y":0.3239617347717285,"z":32.0}{"name":"Underground3","currentGameObject":{"instanceID":-393858},"x":15.0,"y":-0.6760382652282715,"z":32.0}{"name":"Underground3","currentGameObject":{"instanceID":-393870},"x":15.0,"y":-1.6760382652282715,"z":32.0}{"name":"3","currentGameObject":{"instanceID":-393880},"x":16.0,"y":1.0065629482269288,"z":32.0}{"name":"Underground3","currentGameObject":{"instanceID":-393892},"x":16.0,"y":0.006562948226928711,"z":32.0}{"name":"Underground3","currentGameObject":{"instanceID":-393904},"x":16.0,"y":-0.9934370517730713,"z":32.0}{"name":"Underground3","currentGameObject":{"instanceID":-393914},"x":16.0,"y":-1.9934370517730713,"z":32.0}{"name":"3","currentGameObject":{"instanceID":-393924},"x":17.0,"y":1.3420970439910889,"z":32.0}{"name":"Underground3","currentGameObject":{"instanceID":-393936},"x":17.0,"y":0.3420969843864441,"z":32.0}{"name":"Underground3","currentGameObject":{"instanceID":-393948},"x":17.0,"y":-0.6579030156135559,"z":32.0}{"name":"Underground3","currentGameObject":{"instanceID":-393960},"x":17.0,"y":-1.6579029560089112,"z":32.0}{"name":"3","currentGameObject":{"instanceID":-393972},"x":18.0,"y":1.1444728374481202,"z":32.0}{"name":"Underground3","currentGameObject":{"instanceID":-393984},"x":18.0,"y":0.14447280764579774,"z":32.0}{"name":"Underground3","currentGameObject":{"instanceID":-393996},"x":18.0,"y":-0.8555271625518799,"z":32.0}{"name":"Underground3","currentGameObject":{"instanceID":-394008},"x":18.0,"y":-1.8555271625518799,"z":32.0}{"name":"3","currentGameObject":{"instanceID":-394018},"x":19.0,"y":1.3166725635528565,"z":32.0}{"name":"Underground3","currentGameObject":{"instanceID":-394030},"x":19.0,"y":0.3166726231575012,"z":32.0}{"name":"Underground3","currentGameObject":{"instanceID":-394040},"x":19.0,"y":-0.6833273768424988,"z":32.0}{"name":"Underground3","currentGameObject":{"instanceID":-394050},"x":19.0,"y":-1.6833274364471436,"z":32.0}{"name":"3","currentGameObject":{"instanceID":-394062},"x":10.0,"y":1.4453423023223878,"z":33.0}{"name":"Underground3","currentGameObject":{"instanceID":-394082},"x":10.0,"y":0.4453423023223877,"z":33.0}{"name":"Underground3","currentGameObject":{"instanceID":-394092},"x":10.0,"y":-0.5546576976776123,"z":33.0}{"name":"Underground3","currentGameObject":{"instanceID":-394102},"x":10.0,"y":-1.5546576976776124,"z":33.0}{"name":"3","currentGameObject":{"instanceID":-394114},"x":11.0,"y":1.3376559019088746,"z":33.0}{"name":"Underground3","currentGameObject":{"instanceID":-394126},"x":11.0,"y":0.3376559019088745,"z":33.0}{"name":"Underground3","currentGameObject":{"instanceID":-394138},"x":11.0,"y":-0.6623440980911255,"z":33.0}{"name":"Underground3","currentGameObject":{"instanceID":-394148},"x":11.0,"y":-1.6623440980911255,"z":33.0}{"name":"3","currentGameObject":{"instanceID":-394160},"x":12.0,"y":1.3049321174621583,"z":33.0}{"name":"Underground3","currentGameObject":{"instanceID":-394172},"x":12.0,"y":0.3049321472644806,"z":33.0}{"name":"Underground3","currentGameObject":{"instanceID":-394182},"x":12.0,"y":-0.6950678825378418,"z":33.0}{"name":"Underground3","currentGameObject":{"instanceID":-394192},"x":12.0,"y":-1.6950678825378419,"z":33.0}{"name":"3","currentGameObject":{"instanceID":-394202},"x":13.0,"y":1.4029111862182618,"z":33.0}{"name":"Underground3","currentGameObject":{"instanceID":-394214},"x":13.0,"y":0.4029111862182617,"z":33.0}{"name":"Underground3","currentGameObject":{"instanceID":-394224},"x":13.0,"y":-0.5970888137817383,"z":33.0}{"name":"Underground3","currentGameObject":{"instanceID":-394236},"x":13.0,"y":-1.5970888137817383,"z":33.0}{"name":"3","currentGameObject":{"instanceID":-394246},"x":14.0,"y":1.2476475238800049,"z":33.0}{"name":"Underground3","currentGameObject":{"instanceID":-394258},"x":14.0,"y":0.24764755368232728,"z":33.0}{"name":"Underground3","currentGameObject":{"instanceID":-394270},"x":14.0,"y":-0.7523524761199951,"z":33.0}{"name":"Underground3","currentGameObject":{"instanceID":-394282},"x":14.0,"y":-1.7523524761199952,"z":33.0}{"name":"3","currentGameObject":{"instanceID":-394294},"x":15.0,"y":1.4962158203125,"z":33.0}{"name":"Underground3","currentGameObject":{"instanceID":-394314},"x":15.0,"y":0.4962158799171448,"z":33.0}{"name":"Underground3","currentGameObject":{"instanceID":-394324},"x":15.0,"y":-0.5037841200828552,"z":33.0}{"name":"Underground3","currentGameObject":{"instanceID":-394334},"x":15.0,"y":-1.5037841796875,"z":33.0}{"name":"3","currentGameObject":{"instanceID":-394344},"x":16.0,"y":1.2807269096374512,"z":33.0}{"name":"Underground3","currentGameObject":{"instanceID":-394356},"x":16.0,"y":0.28072693943977358,"z":33.0}{"name":"Underground3","currentGameObject":{"instanceID":-394368},"x":16.0,"y":-0.7192730903625488,"z":33.0}{"name":"Underground3","currentGameObject":{"instanceID":-394378},"x":16.0,"y":-1.7192730903625489,"z":33.0}{"name":"3","currentGameObject":{"instanceID":-394388},"x":17.0,"y":1.442805528640747,"z":33.0}{"name":"Underground3","currentGameObject":{"instanceID":-394400},"x":17.0,"y":0.4428054690361023,"z":33.0}{"name":"Underground3","currentGameObject":{"instanceID":-394410},"x":17.0,"y":-0.5571945309638977,"z":33.0}{"name":"Underground3","currentGameObject":{"instanceID":-394420},"x":17.0,"y":-1.557194471359253,"z":33.0}{"name":"3","currentGameObject":{"instanceID":-394432},"x":18.0,"y":1.1017495393753052,"z":33.0}{"name":"Underground3","currentGameObject":{"instanceID":-394444},"x":18.0,"y":0.10174953937530518,"z":33.0}{"name":"Underground3","currentGameObject":{"instanceID":-394454},"x":18.0,"y":-0.8982504606246948,"z":33.0}{"name":"Underground3","currentGameObject":{"instanceID":-394464},"x":18.0,"y":-1.8982504606246949,"z":33.0}{"name":"3","currentGameObject":{"instanceID":-394474},"x":19.0,"y":1.4297747611999512,"z":33.0}{"name":"Underground3","currentGameObject":{"instanceID":-394486},"x":19.0,"y":0.42977482080459597,"z":33.0}{"name":"Underground3","currentGameObject":{"instanceID":-394498},"x":19.0,"y":-0.570225179195404,"z":33.0}{"name":"Underground3","currentGameObject":{"instanceID":-394510},"x":19.0,"y":-1.5702252388000489,"z":33.0}{"name":"3","currentGameObject":{"instanceID":-394520},"x":10.0,"y":1.0937106609344483,"z":34.0}{"name":"Underground3","currentGameObject":{"instanceID":-394532},"x":10.0,"y":0.09371060132980347,"z":34.0}{"name":"Underground3","currentGameObject":{"instanceID":-394542},"x":10.0,"y":-0.9062893986701965,"z":34.0}{"name":"Underground3","currentGameObject":{"instanceID":-394552},"x":10.0,"y":-1.9062893390655518,"z":34.0}{"name":"3","currentGameObject":{"instanceID":-394564},"x":11.0,"y":1.3934838771820069,"z":34.0}{"name":"Underground3","currentGameObject":{"instanceID":-394576},"x":11.0,"y":0.39348387718200686,"z":34.0}{"name":"Underground3","currentGameObject":{"instanceID":-394588},"x":11.0,"y":-0.6065161228179932,"z":34.0}{"name":"Underground3","currentGameObject":{"instanceID":-394600},"x":11.0,"y":-1.6065161228179932,"z":34.0}{"name":"3","currentGameObject":{"instanceID":-394610},"x":12.0,"y":1.3373521566390992,"z":34.0}{"name":"Underground3","currentGameObject":{"instanceID":-394622},"x":12.0,"y":0.3373521566390991,"z":34.0}{"name":"Underground3","currentGameObject":{"instanceID":-394632},"x":12.0,"y":-0.6626478433609009,"z":34.0}{"name":"Underground3","currentGameObject":{"instanceID":-394642},"x":12.0,"y":-1.6626478433609009,"z":34.0}{"name":"3","currentGameObject":{"instanceID":-394652},"x":13.0,"y":1.4398419857025147,"z":34.0}{"name":"Underground3","currentGameObject":{"instanceID":-394664},"x":13.0,"y":0.4398420453071594,"z":34.0}{"name":"Underground3","currentGameObject":{"instanceID":-394674},"x":13.0,"y":-0.5601579546928406,"z":34.0}{"name":"Underground3","currentGameObject":{"instanceID":-394684},"x":13.0,"y":-1.5601580142974854,"z":34.0}{"name":"3","currentGameObject":{"instanceID":-394694},"x":14.0,"y":1.0920674800872803,"z":34.0}{"name":"Underground3","currentGameObject":{"instanceID":-394706},"x":14.0,"y":0.09206753969192505,"z":34.0}{"name":"Underground3","currentGameObject":{"instanceID":-394718},"x":14.0,"y":-0.907932460308075,"z":34.0}{"name":"Underground3","currentGameObject":{"instanceID":-394728},"x":14.0,"y":-1.9079325199127198,"z":34.0}{"name":"3","currentGameObject":{"instanceID":-394738},"x":15.0,"y":1.2268097400665284,"z":34.0}{"name":"Underground3","currentGameObject":{"instanceID":-394750},"x":15.0,"y":0.2268097698688507,"z":34.0}{"name":"Underground3","currentGameObject":{"instanceID":-394762},"x":15.0,"y":-0.7731902599334717,"z":34.0}{"name":"Underground3","currentGameObject":{"instanceID":-394774},"x":15.0,"y":-1.7731902599334717,"z":34.0}{"name":"3","currentGameObject":{"instanceID":-394786},"x":16.0,"y":1.048509120941162,"z":34.0}{"name":"Underground3","currentGameObject":{"instanceID":-394798},"x":16.0,"y":0.048509180545806888,"z":34.0}{"name":"Underground3","currentGameObject":{"instanceID":-394810},"x":16.0,"y":-0.9514908194541931,"z":34.0}{"name":"Underground3","currentGameObject":{"instanceID":-394822},"x":16.0,"y":-1.951490879058838,"z":34.0}{"name":"3","currentGameObject":{"instanceID":-394834},"x":17.0,"y":1.2730114459991456,"z":34.0}{"name":"Underground3","currentGameObject":{"instanceID":-394854},"x":17.0,"y":0.2730114758014679,"z":34.0}{"name":"Underground3","currentGameObject":{"instanceID":-394866},"x":17.0,"y":-0.7269885540008545,"z":34.0}{"name":"Underground3","currentGameObject":{"instanceID":-394876},"x":17.0,"y":-1.7269885540008546,"z":34.0}{"name":"3","currentGameObject":{"instanceID":-394886},"x":18.0,"y":1.006807565689087,"z":34.0}{"name":"Underground3","currentGameObject":{"instanceID":-394898},"x":18.0,"y":0.0068076252937316898,"z":34.0}{"name":"Underground3","currentGameObject":{"instanceID":-394908},"x":18.0,"y":-0.9931923747062683,"z":34.0}{"name":"Underground3","currentGameObject":{"instanceID":-394920},"x":18.0,"y":-1.993192434310913,"z":34.0}{"name":"3","currentGameObject":{"instanceID":-394932},"x":19.0,"y":1.3547394275665284,"z":34.0}{"name":"Underground3","currentGameObject":{"instanceID":-394944},"x":19.0,"y":0.3547394871711731,"z":34.0}{"name":"Underground3","currentGameObject":{"instanceID":-394954},"x":19.0,"y":-0.6452605128288269,"z":34.0}{"name":"Underground3","currentGameObject":{"instanceID":-394966},"x":19.0,"y":-1.6452605724334717,"z":34.0}{"name":"3","currentGameObject":{"instanceID":-394978},"x":10.0,"y":1.401679515838623,"z":35.0}{"name":"Underground3","currentGameObject":{"instanceID":-394990},"x":10.0,"y":0.4016795754432678,"z":35.0}{"name":"Underground3","currentGameObject":{"instanceID":-395002},"x":10.0,"y":-0.5983204245567322,"z":35.0}{"name":"Underground3","currentGameObject":{"instanceID":-395014},"x":10.0,"y":-1.598320484161377,"z":35.0}{"name":"3","currentGameObject":{"instanceID":-395024},"x":11.0,"y":1.0534123182296754,"z":35.0}{"name":"Underground3","currentGameObject":{"instanceID":-395036},"x":11.0,"y":0.05341231822967529,"z":35.0}{"name":"Underground3","currentGameObject":{"instanceID":-395046},"x":11.0,"y":-0.9465876817703247,"z":35.0}{"name":"Underground3","currentGameObject":{"instanceID":-395058},"x":11.0,"y":-1.9465876817703248,"z":35.0}{"name":"3","currentGameObject":{"instanceID":-395070},"x":12.0,"y":1.128808856010437,"z":35.0}{"name":"Underground3","currentGameObject":{"instanceID":-395082},"x":12.0,"y":0.12880882620811463,"z":35.0}{"name":"Underground3","currentGameObject":{"instanceID":-395092},"x":12.0,"y":-0.871191143989563,"z":35.0}{"name":"Underground3","currentGameObject":{"instanceID":-395102},"x":12.0,"y":-1.871191143989563,"z":35.0}{"name":"3","currentGameObject":{"instanceID":-395114},"x":13.0,"y":1.340590000152588,"z":35.0}{"name":"Underground3","currentGameObject":{"instanceID":-395126},"x":13.0,"y":0.3405899405479431,"z":35.0}{"name":"Underground3","currentGameObject":{"instanceID":-395138},"x":13.0,"y":-0.6594100594520569,"z":35.0}{"name":"Underground3","currentGameObject":{"instanceID":-395150},"x":13.0,"y":-1.659409999847412,"z":35.0}{"name":"3","currentGameObject":{"instanceID":-395162},"x":14.0,"y":1.2248183488845826,"z":35.0}{"name":"Underground3","currentGameObject":{"instanceID":-395182},"x":14.0,"y":0.2248183786869049,"z":35.0}{"name":"Underground3","currentGameObject":{"instanceID":-395192},"x":14.0,"y":-0.7751816511154175,"z":35.0}{"name":"Underground3","currentGameObject":{"instanceID":-395202},"x":14.0,"y":-1.7751816511154175,"z":35.0}{"name":"3","currentGameObject":{"instanceID":-395212},"x":15.0,"y":1.1876201629638672,"z":35.0}{"name":"Underground3","currentGameObject":{"instanceID":-395224},"x":15.0,"y":0.1876201331615448,"z":35.0}{"name":"Underground3","currentGameObject":{"instanceID":-395234},"x":15.0,"y":-0.8123798370361328,"z":35.0}{"name":"Underground3","currentGameObject":{"instanceID":-395246},"x":15.0,"y":-1.8123798370361329,"z":35.0}{"name":"3","currentGameObject":{"instanceID":-395258},"x":16.0,"y":1.1037977933883668,"z":35.0}{"name":"Underground3","currentGameObject":{"instanceID":-395270},"x":16.0,"y":0.1037977933883667,"z":35.0}{"name":"Underground3","currentGameObject":{"instanceID":-395280},"x":16.0,"y":-0.8962022066116333,"z":35.0}{"name":"Underground3","currentGameObject":{"instanceID":-395290},"x":16.0,"y":-1.8962022066116334,"z":35.0}{"name":"3","currentGameObject":{"instanceID":-395302},"x":17.0,"y":1.4750714302062989,"z":35.0}{"name":"Underground3","currentGameObject":{"instanceID":-395322},"x":17.0,"y":0.47507143020629885,"z":35.0}{"name":"Underground3","currentGameObject":{"instanceID":-395334},"x":17.0,"y":-0.5249285697937012,"z":35.0}{"name":"Underground3","currentGameObject":{"instanceID":-395344},"x":17.0,"y":-1.5249285697937012,"z":35.0}{"name":"3","currentGameObject":{"instanceID":-395356},"x":18.0,"y":1.0423758029937745,"z":35.0}{"name":"Underground3","currentGameObject":{"instanceID":-395368},"x":18.0,"y":0.04237586259841919,"z":35.0}{"name":"Underground3","currentGameObject":{"instanceID":-395378},"x":18.0,"y":-0.9576241374015808,"z":35.0}{"name":"Underground3","currentGameObject":{"instanceID":-395388},"x":18.0,"y":-1.9576241970062256,"z":35.0}{"name":"3","currentGameObject":{"instanceID":-395398},"x":19.0,"y":1.2080004215240479,"z":35.0}{"name":"Underground3","currentGameObject":{"instanceID":-395410},"x":19.0,"y":0.20800045132637025,"z":35.0}{"name":"Underground3","currentGameObject":{"instanceID":-395420},"x":19.0,"y":-0.7919995784759522,"z":35.0}{"name":"Underground3","currentGameObject":{"instanceID":-395430},"x":19.0,"y":-1.7919995784759522,"z":35.0}{"name":"3","currentGameObject":{"instanceID":-395440},"x":10.0,"y":1.4952430725097657,"z":36.0}{"name":"Underground3","currentGameObject":{"instanceID":-395460},"x":10.0,"y":0.4952431321144104,"z":36.0}{"name":"Underground3","currentGameObject":{"instanceID":-395470},"x":10.0,"y":-0.5047568678855896,"z":36.0}{"name":"Underground3","currentGameObject":{"instanceID":-395482},"x":10.0,"y":-1.5047569274902344,"z":36.0}{"name":"3","currentGameObject":{"instanceID":-395494},"x":11.0,"y":1.4238427877426148,"z":36.0}{"name":"Underground3","currentGameObject":{"instanceID":-395514},"x":11.0,"y":0.42384278774261477,"z":36.0}{"name":"Underground3","currentGameObject":{"instanceID":-395526},"x":11.0,"y":-0.5761572122573853,"z":36.0}{"name":"Underground3","currentGameObject":{"instanceID":-395536},"x":11.0,"y":-1.5761572122573853,"z":36.0}{"name":"3","currentGameObject":{"instanceID":-395546},"x":12.0,"y":1.2071374654769898,"z":36.0}{"name":"Underground3","currentGameObject":{"instanceID":-395558},"x":12.0,"y":0.20713749527931214,"z":36.0}{"name":"Underground3","currentGameObject":{"instanceID":-395568},"x":12.0,"y":-0.7928625345230103,"z":36.0}{"name":"Underground3","currentGameObject":{"instanceID":-395578},"x":12.0,"y":-1.7928625345230103,"z":36.0}{"name":"3","currentGameObject":{"instanceID":-395590},"x":13.0,"y":1.22177255153656,"z":36.0}{"name":"Underground3","currentGameObject":{"instanceID":-395602},"x":13.0,"y":0.22177252173423768,"z":36.0}{"name":"Underground3","currentGameObject":{"instanceID":-395614},"x":13.0,"y":-0.7782274484634399,"z":36.0}{"name":"Underground3","currentGameObject":{"instanceID":-395626},"x":13.0,"y":-1.77822744846344,"z":36.0}{"name":"3","currentGameObject":{"instanceID":-395636},"x":14.0,"y":1.4303183555603028,"z":36.0}{"name":"Underground3","currentGameObject":{"instanceID":-395648},"x":14.0,"y":0.4303184151649475,"z":36.0}{"name":"Underground3","currentGameObject":{"instanceID":-395660},"x":14.0,"y":-0.5696815848350525,"z":36.0}{"name":"Underground3","currentGameObject":{"instanceID":-395672},"x":14.0,"y":-1.5696816444396973,"z":36.0}{"name":"3","currentGameObject":{"instanceID":-395684},"x":15.0,"y":1.0369799137115479,"z":36.0}{"name":"Underground3","currentGameObject":{"instanceID":-395696},"x":15.0,"y":0.03697991371154785,"z":36.0}{"name":"Underground3","currentGameObject":{"instanceID":-395706},"x":15.0,"y":-0.9630200862884522,"z":36.0}{"name":"Underground3","currentGameObject":{"instanceID":-395718},"x":15.0,"y":-1.9630200862884522,"z":36.0}{"name":"3","currentGameObject":{"instanceID":-395728},"x":16.0,"y":1.02692449092865,"z":36.0}{"name":"Underground3","currentGameObject":{"instanceID":-395748},"x":16.0,"y":0.026924490928649904,"z":36.0}{"name":"Underground3","currentGameObject":{"instanceID":-395758},"x":16.0,"y":-0.9730755090713501,"z":36.0}{"name":"Underground3","currentGameObject":{"instanceID":-395770},"x":16.0,"y":-1.97307550907135,"z":36.0}{"name":"3","currentGameObject":{"instanceID":-395782},"x":17.0,"y":1.2238714694976807,"z":36.0}{"name":"Underground3","currentGameObject":{"instanceID":-395794},"x":17.0,"y":0.22387149930000306,"z":36.0}{"name":"Underground3","currentGameObject":{"instanceID":-395806},"x":17.0,"y":-0.7761285305023193,"z":36.0}{"name":"Underground3","currentGameObject":{"instanceID":-395816},"x":17.0,"y":-1.7761285305023194,"z":36.0}{"name":"3","currentGameObject":{"instanceID":-395828},"x":18.0,"y":1.3029228448867798,"z":36.0}{"name":"Underground3","currentGameObject":{"instanceID":-395848},"x":18.0,"y":0.3029228150844574,"z":36.0}{"name":"Underground3","currentGameObject":{"instanceID":-395858},"x":18.0,"y":-0.6970771551132202,"z":36.0}{"name":"Underground3","currentGameObject":{"instanceID":-395868},"x":18.0,"y":-1.6970771551132203,"z":36.0}{"name":"3","currentGameObject":{"instanceID":-395878},"x":19.0,"y":1.292640209197998,"z":36.0}{"name":"Underground3","currentGameObject":{"instanceID":-395890},"x":19.0,"y":0.29264023900032046,"z":36.0}{"name":"Underground3","currentGameObject":{"instanceID":-395902},"x":19.0,"y":-0.707359790802002,"z":36.0}{"name":"Underground3","currentGameObject":{"instanceID":-395914},"x":19.0,"y":-1.707359790802002,"z":36.0}{"name":"3","currentGameObject":{"instanceID":-395924},"x":10.0,"y":1.0345442295074463,"z":37.0}{"name":"Underground3","currentGameObject":{"instanceID":-395936},"x":10.0,"y":0.034544289112091067,"z":37.0}{"name":"Underground3","currentGameObject":{"instanceID":-395946},"x":10.0,"y":-0.9654557108879089,"z":37.0}{"name":"Underground3","currentGameObject":{"instanceID":-395956},"x":10.0,"y":-1.9654557704925538,"z":37.0}{"name":"3","currentGameObject":{"instanceID":-395968},"x":11.0,"y":1.0256361961364747,"z":37.0}{"name":"Underground3","currentGameObject":{"instanceID":-395980},"x":11.0,"y":0.025636136531829835,"z":37.0}{"name":"Underground3","currentGameObject":{"instanceID":-395990},"x":11.0,"y":-0.9743638634681702,"z":37.0}{"name":"Underground3","currentGameObject":{"instanceID":-396000},"x":11.0,"y":-1.9743638038635255,"z":37.0}{"name":"3","currentGameObject":{"instanceID":-396010},"x":12.0,"y":1.4866535663604737,"z":37.0}{"name":"Underground3","currentGameObject":{"instanceID":-396022},"x":12.0,"y":0.48665350675582888,"z":37.0}{"name":"Underground3","currentGameObject":{"instanceID":-396032},"x":12.0,"y":-0.5133464932441711,"z":37.0}{"name":"Underground3","currentGameObject":{"instanceID":-396042},"x":12.0,"y":-1.5133464336395264,"z":37.0}{"name":"3","currentGameObject":{"instanceID":-396054},"x":13.0,"y":1.134310007095337,"z":37.0}{"name":"Underground3","currentGameObject":{"instanceID":-396066},"x":13.0,"y":0.13430997729301454,"z":37.0}{"name":"Underground3","currentGameObject":{"instanceID":-396078},"x":13.0,"y":-0.8656899929046631,"z":37.0}{"name":"Underground3","currentGameObject":{"instanceID":-396088},"x":13.0,"y":-1.865689992904663,"z":37.0}{"name":"3","currentGameObject":{"instanceID":-396100},"x":14.0,"y":1.1990684270858765,"z":37.0}{"name":"Underground3","currentGameObject":{"instanceID":-396112},"x":14.0,"y":0.19906839728355409,"z":37.0}{"name":"Underground3","currentGameObject":{"instanceID":-396122},"x":14.0,"y":-0.8009315729141235,"z":37.0}{"name":"Underground3","currentGameObject":{"instanceID":-396132},"x":14.0,"y":-1.8009315729141236,"z":37.0}{"name":"3","currentGameObject":{"instanceID":-396144},"x":15.0,"y":1.3967688083648682,"z":37.0}{"name":"Underground3","currentGameObject":{"instanceID":-396156},"x":15.0,"y":0.39676880836486819,"z":37.0}{"name":"Underground3","currentGameObject":{"instanceID":-396166},"x":15.0,"y":-0.6032311916351318,"z":37.0}{"name":"Underground3","currentGameObject":{"instanceID":-396178},"x":15.0,"y":-1.6032311916351319,"z":37.0}{"name":"3","currentGameObject":{"instanceID":-396190},"x":16.0,"y":1.4210739135742188,"z":37.0}{"name":"Underground3","currentGameObject":{"instanceID":-396202},"x":16.0,"y":0.42107391357421877,"z":37.0}{"name":"Underground3","currentGameObject":{"instanceID":-396214},"x":16.0,"y":-0.5789260864257813,"z":37.0}{"name":"Underground3","currentGameObject":{"instanceID":-396224},"x":16.0,"y":-1.5789260864257813,"z":37.0}{"name":"3","currentGameObject":{"instanceID":-396234},"x":17.0,"y":1.2513924837112427,"z":37.0}{"name":"Underground3","currentGameObject":{"instanceID":-396246},"x":17.0,"y":0.2513924539089203,"z":37.0}{"name":"Underground3","currentGameObject":{"instanceID":-396258},"x":17.0,"y":-0.7486075162887573,"z":37.0}{"name":"Underground3","currentGameObject":{"instanceID":-396268},"x":17.0,"y":-1.7486075162887574,"z":37.0}{"name":"3","currentGameObject":{"instanceID":-396278},"x":18.0,"y":1.2683610916137696,"z":37.0}{"name":"Underground3","currentGameObject":{"instanceID":-396290},"x":18.0,"y":0.26836106181144717,"z":37.0}{"name":"Underground3","currentGameObject":{"instanceID":-396302},"x":18.0,"y":-0.7316389083862305,"z":37.0}{"name":"Underground3","currentGameObject":{"instanceID":-396312},"x":18.0,"y":-1.7316389083862305,"z":37.0}{"name":"3","currentGameObject":{"instanceID":-396324},"x":19.0,"y":1.2383464574813843,"z":37.0}{"name":"Underground3","currentGameObject":{"instanceID":-396336},"x":19.0,"y":0.2383464276790619,"z":37.0}{"name":"Underground3","currentGameObject":{"instanceID":-396348},"x":19.0,"y":-0.7616535425186157,"z":37.0}{"name":"Underground3","currentGameObject":{"instanceID":-396360},"x":19.0,"y":-1.7616535425186158,"z":37.0}{"name":"3","currentGameObject":{"instanceID":-396372},"x":10.0,"y":1.0851095914840699,"z":38.0}{"name":"Underground3","currentGameObject":{"instanceID":-396384},"x":10.0,"y":0.08510959148406983,"z":38.0}{"name":"Underground3","currentGameObject":{"instanceID":-396396},"x":10.0,"y":-0.9148904085159302,"z":38.0}{"name":"Underground3","currentGameObject":{"instanceID":-396406},"x":10.0,"y":-1.9148904085159302,"z":38.0}{"name":"3","currentGameObject":{"instanceID":-396416},"x":11.0,"y":1.0361740589141846,"z":38.0}{"name":"Underground3","currentGameObject":{"instanceID":-396428},"x":11.0,"y":0.036174118518829349,"z":38.0}{"name":"Underground3","currentGameObject":{"instanceID":-396438},"x":11.0,"y":-0.9638258814811707,"z":38.0}{"name":"Underground3","currentGameObject":{"instanceID":-396448},"x":11.0,"y":-1.9638259410858155,"z":38.0}{"name":"3","currentGameObject":{"instanceID":-396460},"x":12.0,"y":1.343729853630066,"z":38.0}{"name":"Underground3","currentGameObject":{"instanceID":-396472},"x":12.0,"y":0.3437298536300659,"z":38.0}{"name":"Underground3","currentGameObject":{"instanceID":-396484},"x":12.0,"y":-0.6562701463699341,"z":38.0}{"name":"Underground3","currentGameObject":{"instanceID":-396494},"x":12.0,"y":-1.656270146369934,"z":38.0}{"name":"3","currentGameObject":{"instanceID":-396504},"x":13.0,"y":1.0193169116973878,"z":38.0}{"name":"Underground3","currentGameObject":{"instanceID":-396516},"x":13.0,"y":0.01931685209274292,"z":38.0}{"name":"Underground3","currentGameObject":{"instanceID":-396528},"x":13.0,"y":-0.9806831479072571,"z":38.0}{"name":"Underground3","currentGameObject":{"instanceID":-396538},"x":13.0,"y":-1.9806830883026124,"z":38.0}{"name":"3","currentGameObject":{"instanceID":-396548},"x":14.0,"y":1.3349194526672364,"z":38.0}{"name":"Underground3","currentGameObject":{"instanceID":-396560},"x":14.0,"y":0.33491939306259158,"z":38.0}{"name":"Underground3","currentGameObject":{"instanceID":-396570},"x":14.0,"y":-0.6650806069374085,"z":38.0}{"name":"Underground3","currentGameObject":{"instanceID":-396582},"x":14.0,"y":-1.6650805473327637,"z":38.0}{"name":"3","currentGameObject":{"instanceID":-396594},"x":15.0,"y":1.4290252923965455,"z":38.0}{"name":"Underground3","currentGameObject":{"instanceID":-396606},"x":15.0,"y":0.4290252923965454,"z":38.0}{"name":"Underground3","currentGameObject":{"instanceID":-396616},"x":15.0,"y":-0.5709747076034546,"z":38.0}{"name":"Underground3","currentGameObject":{"instanceID":-396626},"x":15.0,"y":-1.5709747076034547,"z":38.0}{"name":"3","currentGameObject":{"instanceID":-396636},"x":16.0,"y":1.411585807800293,"z":38.0}{"name":"Underground3","currentGameObject":{"instanceID":-396648},"x":16.0,"y":0.41158586740493777,"z":38.0}{"name":"Underground3","currentGameObject":{"instanceID":-396658},"x":16.0,"y":-0.5884141325950623,"z":38.0}{"name":"Underground3","currentGameObject":{"instanceID":-396668},"x":16.0,"y":-1.588414192199707,"z":38.0}{"name":"3","currentGameObject":{"instanceID":-396678},"x":17.0,"y":1.3237755298614503,"z":38.0}{"name":"Underground3","currentGameObject":{"instanceID":-396690},"x":17.0,"y":0.32377558946609499,"z":38.0}{"name":"Underground3","currentGameObject":{"instanceID":-396700},"x":17.0,"y":-0.676224410533905,"z":38.0}{"name":"Underground3","currentGameObject":{"instanceID":-396712},"x":17.0,"y":-1.6762244701385499,"z":38.0}{"name":"3","currentGameObject":{"instanceID":-396722},"x":18.0,"y":1.411704182624817,"z":38.0}{"name":"Underground3","currentGameObject":{"instanceID":-396734},"x":18.0,"y":0.4117041826248169,"z":38.0}{"name":"Underground3","currentGameObject":{"instanceID":-396744},"x":18.0,"y":-0.5882958173751831,"z":38.0}{"name":"Underground3","currentGameObject":{"instanceID":-396754},"x":18.0,"y":-1.588295817375183,"z":38.0}{"name":"3","currentGameObject":{"instanceID":-396766},"x":19.0,"y":1.0363905429840088,"z":38.0}{"name":"Underground3","currentGameObject":{"instanceID":-396778},"x":19.0,"y":0.036390483379364017,"z":38.0}{"name":"Underground3","currentGameObject":{"instanceID":-396790},"x":19.0,"y":-0.963609516620636,"z":38.0}{"name":"Underground3","currentGameObject":{"instanceID":-396802},"x":19.0,"y":-1.9636094570159913,"z":38.0}{"name":"3","currentGameObject":{"instanceID":-396814},"x":10.0,"y":1.0334367752075196,"z":39.0}{"name":"Underground3","currentGameObject":{"instanceID":-396826},"x":10.0,"y":0.03343683481216431,"z":39.0}{"name":"Underground3","currentGameObject":{"instanceID":-396836},"x":10.0,"y":-0.9665631651878357,"z":39.0}{"name":"Underground3","currentGameObject":{"instanceID":-396846},"x":10.0,"y":-1.9665632247924805,"z":39.0}{"name":"3","currentGameObject":{"instanceID":-396856},"x":11.0,"y":1.0895469188690186,"z":39.0}{"name":"Underground3","currentGameObject":{"instanceID":-396868},"x":11.0,"y":0.08954685926437378,"z":39.0}{"name":"Underground3","currentGameObject":{"instanceID":-396878},"x":11.0,"y":-0.9104531407356262,"z":39.0}{"name":"Underground3","currentGameObject":{"instanceID":-396888},"x":11.0,"y":-1.9104530811309815,"z":39.0}{"name":"3","currentGameObject":{"instanceID":-396900},"x":12.0,"y":1.445235252380371,"z":39.0}{"name":"Underground3","currentGameObject":{"instanceID":-396912},"x":12.0,"y":0.4452352523803711,"z":39.0}{"name":"Underground3","currentGameObject":{"instanceID":-396922},"x":12.0,"y":-0.5547647476196289,"z":39.0}{"name":"Underground3","currentGameObject":{"instanceID":-396932},"x":12.0,"y":-1.554764747619629,"z":39.0}{"name":"3","currentGameObject":{"instanceID":-396942},"x":13.0,"y":1.0749990940093995,"z":39.0}{"name":"Underground3","currentGameObject":{"instanceID":-396954},"x":13.0,"y":0.07499903440475464,"z":39.0}{"name":"Underground3","currentGameObject":{"instanceID":-396966},"x":13.0,"y":-0.9250009655952454,"z":39.0}{"name":"Underground3","currentGameObject":{"instanceID":-396978},"x":13.0,"y":-1.9250009059906006,"z":39.0}{"name":"3","currentGameObject":{"instanceID":-396988},"x":14.0,"y":1.0228357315063477,"z":39.0}{"name":"Underground3","currentGameObject":{"instanceID":-397000},"x":14.0,"y":0.02283567190170288,"z":39.0}{"name":"Underground3","currentGameObject":{"instanceID":-397010},"x":14.0,"y":-0.9771643280982971,"z":39.0}{"name":"Underground3","currentGameObject":{"instanceID":-397020},"x":14.0,"y":-1.9771642684936524,"z":39.0}{"name":"3","currentGameObject":{"instanceID":-397032},"x":15.0,"y":1.037099003791809,"z":39.0}{"name":"Underground3","currentGameObject":{"instanceID":-397044},"x":15.0,"y":0.03709900379180908,"z":39.0}{"name":"Underground3","currentGameObject":{"instanceID":-397056},"x":15.0,"y":-0.9629009962081909,"z":39.0}{"name":"Underground3","currentGameObject":{"instanceID":-397066},"x":15.0,"y":-1.962900996208191,"z":39.0}{"name":"3","currentGameObject":{"instanceID":-397076},"x":16.0,"y":1.3125674724578858,"z":39.0}{"name":"Underground3","currentGameObject":{"instanceID":-397088},"x":16.0,"y":0.31256747245788576,"z":39.0}{"name":"Underground3","currentGameObject":{"instanceID":-397100},"x":16.0,"y":-0.6874325275421143,"z":39.0}{"name":"Underground3","currentGameObject":{"instanceID":-397112},"x":16.0,"y":-1.6874325275421143,"z":39.0}{"name":"3","currentGameObject":{"instanceID":-397124},"x":17.0,"y":1.0211262702941895,"z":39.0}{"name":"Underground3","currentGameObject":{"instanceID":-397136},"x":17.0,"y":0.02112632989883423,"z":39.0}{"name":"Underground3","currentGameObject":{"instanceID":-397148},"x":17.0,"y":-0.9788736701011658,"z":39.0}{"name":"Underground3","currentGameObject":{"instanceID":-397158},"x":17.0,"y":-1.9788737297058106,"z":39.0}{"name":"3","currentGameObject":{"instanceID":-397170},"x":18.0,"y":1.469693660736084,"z":39.0}{"name":"Underground3","currentGameObject":{"instanceID":-397182},"x":18.0,"y":0.4696936011314392,"z":39.0}{"name":"Underground3","currentGameObject":{"instanceID":-397192},"x":18.0,"y":-0.5303063988685608,"z":39.0}{"name":"Underground3","currentGameObject":{"instanceID":-397202},"x":18.0,"y":-1.530306339263916,"z":39.0}{"name":"3","currentGameObject":{"instanceID":-397214},"x":19.0,"y":1.420607566833496,"z":39.0}{"name":"Underground3","currentGameObject":{"instanceID":-397226},"x":19.0,"y":0.4206075072288513,"z":39.0}{"name":"Underground3","currentGameObject":{"instanceID":-397238},"x":19.0,"y":-0.5793924927711487,"z":39.0}{"name":"Underground3","currentGameObject":{"instanceID":-397250},"x":19.0,"y":-1.579392433166504,"z":39.0}{"name":"3","currentGameObject":{"instanceID":-397262},"x":10.0,"y":1.4728217124938965,"z":40.0}{"name":"Underground3","currentGameObject":{"instanceID":-397274},"x":10.0,"y":0.47282177209854128,"z":40.0}{"name":"Underground3","currentGameObject":{"instanceID":-397286},"x":10.0,"y":-0.5271782279014587,"z":40.0}{"name":"Underground3","currentGameObject":{"instanceID":-397296},"x":10.0,"y":-1.5271782875061036,"z":40.0}{"name":"3","currentGameObject":{"instanceID":-397306},"x":11.0,"y":1.252565622329712,"z":40.0}{"name":"Underground3","currentGameObject":{"instanceID":-397318},"x":11.0,"y":0.2525656521320343,"z":40.0}{"name":"Underground3","currentGameObject":{"instanceID":-397330},"x":11.0,"y":-0.7474343776702881,"z":40.0}{"name":"Underground3","currentGameObject":{"instanceID":-397340},"x":11.0,"y":-1.747434377670288,"z":40.0}{"name":"3","currentGameObject":{"instanceID":-397350},"x":12.0,"y":1.1944602727890015,"z":40.0}{"name":"Underground3","currentGameObject":{"instanceID":-397362},"x":12.0,"y":0.19446030259132386,"z":40.0}{"name":"Underground3","currentGameObject":{"instanceID":-397374},"x":12.0,"y":-0.8055397272109985,"z":40.0}{"name":"Underground3","currentGameObject":{"instanceID":-397386},"x":12.0,"y":-1.8055397272109986,"z":40.0}{"name":"3","currentGameObject":{"instanceID":-397398},"x":13.0,"y":1.1678102016448975,"z":40.0}{"name":"Underground3","currentGameObject":{"instanceID":-397410},"x":13.0,"y":0.16781017184257508,"z":40.0}{"name":"Underground3","currentGameObject":{"instanceID":-397420},"x":13.0,"y":-0.8321897983551025,"z":40.0}{"name":"Underground3","currentGameObject":{"instanceID":-397432},"x":13.0,"y":-1.8321897983551026,"z":40.0}{"name":"3","currentGameObject":{"instanceID":-397444},"x":14.0,"y":1.4283339977264405,"z":40.0}{"name":"Underground3","currentGameObject":{"instanceID":-397456},"x":14.0,"y":0.42833399772644045,"z":40.0}{"name":"Underground3","currentGameObject":{"instanceID":-397466},"x":14.0,"y":-0.5716660022735596,"z":40.0}{"name":"Underground3","currentGameObject":{"instanceID":-397478},"x":14.0,"y":-1.5716660022735596,"z":40.0}{"name":"3","currentGameObject":{"instanceID":-397490},"x":15.0,"y":1.177996277809143,"z":40.0}{"name":"Underground3","currentGameObject":{"instanceID":-397502},"x":15.0,"y":0.17799630761146546,"z":40.0}{"name":"Underground3","currentGameObject":{"instanceID":-397514},"x":15.0,"y":-0.8220037221908569,"z":40.0}{"name":"Underground3","currentGameObject":{"instanceID":-397526},"x":15.0,"y":-1.822003722190857,"z":40.0}{"name":"3","currentGameObject":{"instanceID":-397536},"x":16.0,"y":1.1968801021575928,"z":40.0}{"name":"Underground3","currentGameObject":{"instanceID":-397548},"x":16.0,"y":0.19688013195991517,"z":40.0}{"name":"Underground3","currentGameObject":{"instanceID":-397560},"x":16.0,"y":-0.8031198978424072,"z":40.0}{"name":"Underground3","currentGameObject":{"instanceID":-397572},"x":16.0,"y":-1.8031198978424073,"z":40.0}{"name":"3","currentGameObject":{"instanceID":-397582},"x":17.0,"y":1.4271481037139893,"z":40.0}{"name":"Underground3","currentGameObject":{"instanceID":-397594},"x":17.0,"y":0.42714810371398928,"z":40.0}{"name":"Underground3","currentGameObject":{"instanceID":-397604},"x":17.0,"y":-0.5728518962860107,"z":40.0}{"name":"Underground3","currentGameObject":{"instanceID":-397614},"x":17.0,"y":-1.5728518962860108,"z":40.0}{"name":"3","currentGameObject":{"instanceID":-397624},"x":18.0,"y":1.4353089332580567,"z":40.0}{"name":"Underground3","currentGameObject":{"instanceID":-397636},"x":18.0,"y":0.43530893325805666,"z":40.0}{"name":"Underground3","currentGameObject":{"instanceID":-397648},"x":18.0,"y":-0.5646910667419434,"z":40.0}{"name":"Underground3","currentGameObject":{"instanceID":-397660},"x":18.0,"y":-1.5646910667419434,"z":40.0}{"name":"3","currentGameObject":{"instanceID":-397672},"x":19.0,"y":1.2589606046676636,"z":40.0}{"name":"Underground3","currentGameObject":{"instanceID":-397692},"x":19.0,"y":0.2589605748653412,"z":40.0}{"name":"Underground3","currentGameObject":{"instanceID":-397702},"x":19.0,"y":-0.7410393953323364,"z":40.0}{"name":"Underground3","currentGameObject":{"instanceID":-397714},"x":19.0,"y":-1.7410393953323365,"z":40.0}